Workbook

Sheet LÉEME
B2: PEPTIDEX · ESTUDIO DE MERCADO DE PRECIOS DE VENTA
B3: Las 118 presentaciones del catálogo, con el precio al que el mercado las vende hoy y el precio al que conviene venderlas. 02.08.2026
B5: QUÉ HAY EN CADA HOJA
B6: MÉXICO · las 118 presentaciones en pesos. La columna amarilla, PRECIO SUGERIDO, es la respuesta.
B7: USA · las mismas 118 en dólares.
B8: BANDAS · el motor. La banda de precio por unidad de cada compuesto, con su fuente. Cambiar un número aquí actualiza las dos hojas de arriba.
B9: FUENTES · cada enlace consultado y qué dato salió de él.
B11: CÓMO SE LLEGA AL PRECIO SUGERIDO
B12: 1 · Se busca el precio real de cada compuesto en el mercado y se expresa por unidad — por mg casi siempre, por UI en la hormona de crecimiento y por ml en el lipotrópico.
B13: 2 · Esa banda por unidad se multiplica por la cantidad de cada presentación. Así el vial de 20 mg sale del mismo número que el de 5 mg, que es como se comporta el mercado.
B14: 3 · El sugerido es el punto medio de la banda, redondeado. Ni el suelo — que es guerra de precio — ni el techo, que sólo lo sostiene una marca ya conocida.
B16: LO QUE HAY QUE MIRAR PRIMERO
... B27: Research Use Only — no para uso humano ni veterinario.

Sheet MÉXICO
B2: PEPTIDEX · PRECIOS DE VENTA — MÉXICO
B3: Precio de mercado y precio sugerido para las 118 presentaciones. La columna amarilla es la respuesta. 02.08.2026
A5: LÍNEA | B5: CÓDIGO | C5: COMPUESTO | D5: CANT. | E5: UNIDAD | F5: TU PRECIO HOY | G5: MERCADO BAJO | H5: MERCADO ALTO | I5: PRECIO SUGERIDO | J5: PRECIO POR UNIDAD | K5: ¿DÓNDE QUEDAS? | L5: CONF. | M5: COMPETIDOR REAL | N5: QUIÉN
A6: BEAUTY | B6: AC | C6: AHK-Cu | D6: 20 | E6: mg | F6: 500 | G6: =BANDAS!$E$9*$D6*BANDAS!$E$5*BANDAS!$E$6 | H6: =BANDAS!$F$9*$D6*BANDAS!$E$5*BANDAS!$E$6 | I6: =ROUND(AVERAGE(G6,H6)/50,0)*50 | J6: =IF($D6=0,"",I6/$D6) | K6: =IF(F6="","",IF(F6<G6,"POR DEBAJO",IF(F6>H6,"POR ENCIMA","EN MERCADO"))) | L6: D
A7: BEAUTY | B7: AC | C7: AHK-Cu | D7: 50 | E7: mg | F7: 1350 | G7: =BANDAS!$E$9*$D7*BANDAS!$E$5*BANDAS!$E$6 | H7: =BANDAS!$F$9*$D7*BANDAS!$E$5*BANDAS!$E$6 | I7: =ROUND(AVERAGE(G7,H7)/50,0)*50 | J7: =IF($D7=0,"",I7/$D7) | K7: =IF(F7="","",IF(F7<G7,"POR DEBAJO",IF(F7>H7,"POR ENCIMA","EN MERCADO"))) | L7: D
A8: BEAUTY | B8: CU | C8: GHK-Cu | D8: 50 | E8: mg | F8: 1150 | G8: =BANDAS!$E$10*$D8*BANDAS!$E$5*BANDAS!$E$6 | H8: =BANDAS!$F$10*$D8*BANDAS!$E$5*BANDAS!$E$6 | I8: =ROUND(AVERAGE(G8,H8)/50,0)*50 | J8: =IF($D8=0,"",I8/$D8) | K8: =IF(F8="","",IF(F8<G8,"POR DEBAJO",IF(F8>H8,"POR ENCIMA","EN MERCADO"))) | L8: V | M8: 520 | N8: EXOMA Peptides
A9: BEAUTY | B9: CU | C9: GHK-Cu | D9: 100 | E9: mg | F9: 1850 | G9: =BANDAS!$E$10*$D9*BANDAS!$E$5*BANDAS!$E$6 | H9: =BANDAS!$F$10*$D9*BANDAS!$E$5*BANDAS!$E$6 | I9: =ROUND(AVERAGE(G9,H9)/50,0)*50 | J9: =IF($D9=0,"",I9/$D9) | K9: =IF(F9="","",IF(F9<G9,"POR DEBAJO",IF(F9>H9,"POR ENCIMA","EN MERCADO"))) | L9: V
A10: BEAUTY | B10: GL | C10: GLOW Blend | D10: 70 | E10: mg | F10: 6400 | G10: =BANDAS!$E$11*$D10*BANDAS!$E$5*BANDAS!$E$6 | H10: =BANDAS!$F$11*$D10*BANDAS!$E$5*BANDAS!$E$6 | I10: =ROUND(AVERAGE(G10,H10)/50,0)*50 | J10: =IF($D10=0,"",I10/$D10) | K10: =IF(F10="","",IF(F10<G10,"POR DEBAJO",IF(F10>H10,"POR ENCIMA","EN MERCADO"))) | L10: D | M10: 2090 | N10: EXOMA Peptides
A11: BEAUTY | B11: GT | C11: Glutathione | D11: 600 | E11: mg | F11: 1100 | G11: =BANDAS!$E$12*$D11*BANDAS!$E$5*BANDAS!$E$6 | H11: =BANDAS!$F$12*$D11*BANDAS!$E$5*BANDAS!$E$6 | I11: =ROUND(AVERAGE(G11,H11)/50,0)*50 | J11: =IF($D11=0,"",I11/$D11) | K11: =IF(F11="","",IF(F11<G11,"POR DEBAJO",IF(F11>H11,"POR ENCIMA","EN MERCADO"))) | L11: D
A12: BEAUTY | B12: GT | C12: Glutathione | D12: 1500 | E12: mg | F12: 2700 | G12: =BANDAS!$E$12*$D12*BANDAS!$E$5*BANDAS!$E$6 | H12: =BANDAS!$F$12*$D12*BANDAS!$E$5*BANDAS!$E$6 | I12: =ROUND(AVERAGE(G12,H12)/50,0)*50 | J12: =IF($D12=0,"",I12/$D12) | K12: =IF(F12="","",IF(F12<G12,"POR DEBAJO",IF(F12>H12,"POR ENCIMA","EN MERCADO"))) | L12: D
A13: BEAUTY | B13: KL | C13: KLOW Blend | D13: 80 | E13: mg | F13: 7400 | G13: =BANDAS!$E$13*$D13*BANDAS!$E$5*BANDAS!$E$6 | H13: =BANDAS!$F$13*$D13*BANDAS!$E$5*BANDAS!$E$6 | I13: =ROUND(AVERAGE(G13,H13)/50,0)*50 | J13: =IF($D13=0,"",I13/$D13) | K13: =IF(F13="","",IF(F13<G13,"POR DEBAJO",IF(F13>H13,"POR ENCIMA","EN MERCADO"))) | L13: D
A14: BEAUTY | B14: KP | C14: KPV | D14: 5 | E14: mg | F14: 500 | G14: =BANDAS!$E$14*$D14*BANDAS!$E$5*BANDAS!$E$6 | H14: =BANDAS!$F$14*$D14*BANDAS!$E$5*BANDAS!$E$6 | I14: =ROUND(AVERAGE(G14,H14)/50,0)*50 | J14: =IF($D14=0,"",I14/$D14) | K14: =IF(F14="","",IF(F14<G14,"POR DEBAJO",IF(F14>H14,"POR ENCIMA","EN MERCADO"))) | L14: D
A15: BEAUTY | B15: KP | C15: KPV | D15: 10 | E15: mg | F15: 850 | G15: =BANDAS!$E$14*$D15*BANDAS!$E$5*BANDAS!$E$6 | H15: =BANDAS!$F$14*$D15*BANDAS!$E$5*BANDAS!$E$6 | I15: =ROUND(AVERAGE(G15,H15)/50,0)*50 | J15: =IF($D15=0,"",I15/$D15) | K15: =IF(F15="","",IF(F15<G15,"POR DEBAJO",IF(F15>H15,"POR ENCIMA","EN MERCADO"))) | L15: D
A16: BEAUTY | B16: MX | C16: Matrixyl | D16: 10 | E16: mg | F16: 2100 | G16: =BANDAS!$E$15*$D16*BANDAS!$E$5*BANDAS!$E$6 | H16: =BANDAS!$F$15*$D16*BANDAS!$E$5*BANDAS!$E$6 | I16: =ROUND(AVERAGE(G16,H16)/50,0)*50 | J16: =IF($D16=0,"",I16/$D16) | K16: =IF(F16="","",IF(F16<G16,"POR DEBAJO",IF(F16>H16,"POR ENCIMA","EN MERCADO"))) | L16: D
A17: BEAUTY | B17: MT1 | C17: Melanotan I | D17: 10 | E17: mg | F17: 1000 | G17: =BANDAS!$E$16*$D17*BANDAS!$E$5*BANDAS!$E$6 | H17: =BANDAS!$F$16*$D17*BANDAS!$E$5*BANDAS!$E$6 | I17: =ROUND(AVERAGE(G17,H17)/50,0)*50 | J17: =IF($D17=0,"",I17/$D17) | K17: =IF(F17="","",IF(F17<G17,"POR DEBAJO",IF(F17>H17,"POR ENCIMA","EN MERCADO"))) | L17: D
A18: BEAUTY | B18: MT2 | C18: Melanotan II | D18: 10 | E18: mg | F18: 1000 | G18: =BANDAS!$E$17*$D18*BANDAS!$E$5*BANDAS!$E$6 | H18: =BANDAS!$F$17*$D18*BANDAS!$E$5*BANDAS!$E$6 | I18: =ROUND(AVERAGE(G18,H18)/50,0)*50 | J18: =IF($D18=0,"",I18/$D18) | K18: =IF(F18="","",IF(F18<G18,"POR DEBAJO",IF(F18>H18,"POR ENCIMA","EN MERCADO"))) | L18: V
A19: BEAUTY | B19: OT | C19: Oxytocin | D19: 5 | E19: mg | F19: 1000 | G19: =BANDAS!$E$18*$D19*BANDAS!$E$5*BANDAS!$E$6 | H19: =BANDAS!$F$18*$D19*BANDAS!$E$5*BANDAS!$E$6 | I19: =ROUND(AVERAGE(G19,H19)/50,0)*50 | J19: =IF($D19=0,"",I19/$D19) | K19: =IF(F19="","",IF(F19<G19,"POR DEBAJO",IF(F19>H19,"POR ENCIMA","EN MERCADO"))) | L19: D
A20: BEAUTY | B20: PT | C20: PT-141 | D20: 10 | E20: mg | F20: 1000 | G20: =BANDAS!$E$19*$D20*BANDAS!$E$5*BANDAS!$E$6 | H20: =BANDAS!$F$19*$D20*BANDAS!$E$5*BANDAS!$E$6 | I20: =ROUND(AVERAGE(G20,H20)/50,0)*50 | J20: =IF($D20=0,"",I20/$D20) | K20: =IF(F20="","",IF(F20<G20,"POR DEBAJO",IF(F20>H20,"POR ENCIMA","EN MERCADO"))) | L20: V
A21: BEAUTY | B21: NP8 | C21: Snap-8 | D21: 10 | E21: mg | F21: 850 | G21: =BANDAS!$E$20*$D21*BANDAS!$E$5*BANDAS!$E$6 | H21: =BANDAS!$F$20*$D21*BANDAS!$E$5*BANDAS!$E$6 | I21: =ROUND(AVERAGE(G21,H21)/50,0)*50 | J21: =IF($D21=0,"",I21/$D21) | K21: =IF(F21="","",IF(F21<G21,"POR DEBAJO",IF(F21>H21,"POR ENCIMA","EN MERCADO"))) | L21: D
A22: FITNESS | B22: AM | C22: 5-Amino-1MQ | D22: 5 | E22: mg | F22: 300 | G22: =BANDAS!$E$21*$D22*BANDAS!$E$5*BANDAS!$E$6 | H22: =BANDAS!$F$21*$D22*BANDAS!$E$5*BANDAS!$E$6 | I22: =ROUND(AVERAGE(G22,H22)/50,0)*50 | J22: =IF($D22=0,"",I22/$D22) | K22: =IF(F22="","",IF(F22<G22,"POR DEBAJO",IF(F22>H22,"POR ENCIMA","EN MERCADO"))) | L22: D
A23: FITNESS | B23: AM | C23: 5-Amino-1MQ | D23: 10 | E23: mg | F23: 550 | G23: =BANDAS!$E$21*$D23*BANDAS!$E$5*BANDAS!$E$6 | H23: =BANDAS!$F$21*$D23*BANDAS!$E$5*BANDAS!$E$6 | I23: =ROUND(AVERAGE(G23,H23)/50,0)*50 | J23: =IF($D23=0,"",I23/$D23) | K23: =IF(F23="","",IF(F23<G23,"POR DEBAJO",IF(F23>H23,"POR ENCIMA","EN MERCADO"))) | L23: D
A24: FITNESS | B24: AM | C24: 5-Amino-1MQ | D24: 50 | E24: mg | F24: 2350 | G24: =BANDAS!$E$21*$D24*BANDAS!$E$5*BANDAS!$E$6 | H24: =BANDAS!$F$21*$D24*BANDAS!$E$5*BANDAS!$E$6 | I24: =ROUND(AVERAGE(G24,H24)/50,0)*50 | J24: =IF($D24=0,"",I24/$D24) | K24: =IF(F24="","",IF(F24<G24,"POR DEBAJO",IF(F24>H24,"POR ENCIMA","EN MERCADO"))) | L24: D
A25: FITNESS | B25: AR | C25: AICAR | D25: 50 | E25: mg | F25: 1350 | G25: =BANDAS!$E$22*$D25*BANDAS!$E$5*BANDAS!$E$6 | H25: =BANDAS!$F$22*$D25*BANDAS!$E$5*BANDAS!$E$6 | I25: =ROUND(AVERAGE(G25,H25)/50,0)*50 | J25: =IF($D25=0,"",I25/$D25) | K25: =IF(F25="","",IF(F25<G25,"POR DEBAJO",IF(F25>H25,"POR ENCIMA","EN MERCADO"))) | L25: D
A26: FITNESS | B26: AR | C26: AICAR | D26: 100 | E26: mg | F26: 2700 | G26: =BANDAS!$E$22*$D26*BANDAS!$E$5*BANDAS!$E$6 | H26: =BANDAS!$F$22*$D26*BANDAS!$E$5*BANDAS!$E$6 | I26: =ROUND(AVERAGE(G26,H26)/50,0)*50 | J26: =IF($D26=0,"",I26/$D26) | K26: =IF(F26="","",IF(F26<G26,"POR DEBAJO",IF(F26>H26,"POR ENCIMA","EN MERCADO"))) | L26: D
A27: FITNESS | B27: AD | C27: AOD-9604 | D27: 5 | E27: mg | F27: 800 | G27: =BANDAS!$E$23*$D27*BANDAS!$E$5*BANDAS!$E$6 | H27: =BANDAS!$F$23*$D27*BANDAS!$E$5*BANDAS!$E$6 | I27: =ROUND(AVERAGE(G27,H27)/50,0)*50 | J27: =IF($D27=0,"",I27/$D27) | K27: =IF(F27="","",IF(F27<G27,"POR DEBAJO",IF(F27>H27,"POR ENCIMA","EN MERCADO"))) | L27: D
A28: FITNESS | B28: AD | C28: AOD-9604 | D28: 10 | E28: mg | F28: 1450 | G28: =BANDAS!$E$23*$D28*BANDAS!$E$5*BANDAS!$E$6 | H28: =BANDAS!$F$23*$D28*BANDAS!$E$5*BANDAS!$E$6 | I28: =ROUND(AVERAGE(G28,H28)/50,0)*50 | J28: =IF($D28=0,"",I28/$D28) | K28: =IF(F28="","",IF(F28<G28,"POR DEBAJO",IF(F28>H28,"POR ENCIMA","EN MERCADO"))) | L28: D
A29: FITNESS | B29: AX | C29: Adamax | D29: 10 | E29: mg | F29: 2100 | G29: =BANDAS!$E$24*$D29*BANDAS!$E$5*BANDAS!$E$6 | H29: =BANDAS!$F$24*$D29*BANDAS!$E$5*BANDAS!$E$6 | I29: =ROUND(AVERAGE(G29,H29)/50,0)*50 | J29: =IF($D29=0,"",I29/$D29) | K29: =IF(F29="","",IF(F29<G29,"POR DEBAJO",IF(F29>H29,"POR ENCIMA","EN MERCADO"))) | L29: D
A30: FITNESS | B30: APT | C30: Adipotide | D30: 5 | E30: mg | F30: 1000 | G30: =BANDAS!$E$25*$D30*BANDAS!$E$5*BANDAS!$E$6 | H30: =BANDAS!$F$25*$D30*BANDAS!$E$5*BANDAS!$E$6 | I30: =ROUND(AVERAGE(G30,H30)/50,0)*50 | J30: =IF($D30=0,"",I30/$D30) | K30: =IF(F30="","",IF(F30<G30,"POR DEBAJO",IF(F30>H30,"POR ENCIMA","EN MERCADO"))) | L30: D
A31: FITNESS | B31: APT | C31: Adipotide | D31: 10 | E31: mg | F31: 2100 | G31: =BANDAS!$E$25*$D31*BANDAS!$E$5*BANDAS!$E$6 | H31: =BANDAS!$F$25*$D31*BANDAS!$E$5*BANDAS!$E$6 | I31: =ROUND(AVERAGE(G31,H31)/50,0)*50 | J31: =IF($D31=0,"",I31/$D31) | K31: =IF(F31="","",IF(F31<G31,"POR DEBAJO",IF(F31>H31,"POR ENCIMA","EN MERCADO"))) | L31: D
A32: FITNESS | B32: RA | C32: Ara-290 | D32: 10 | E32: mg | F32: 2100 | G32: =BANDAS!$E$26*$D32*BANDAS!$E$5*BANDAS!$E$6 | H32: =BANDAS!$F$26*$D32*BANDAS!$E$5*BANDAS!$E$6 | I32: =ROUND(AVERAGE(G32,H32)/50,0)*50 | J32: =IF($D32=0,"",I32/$D32) | K32: =IF(F32="","",IF(F32<G32,"POR DEBAJO",IF(F32>H32,"POR ENCIMA","EN MERCADO"))) | L32: D
A33: FITNESS | B33: BC | C33: BPC-157 | D33: 5 | E33: mg | F33: 700 | G33: =BANDAS!$E$27*$D33*BANDAS!$E$5*BANDAS!$E$6 | H33: =BANDAS!$F$27*$D33*BANDAS!$E$5*BANDAS!$E$6 | I33: =ROUND(AVERAGE(G33,H33)/50,0)*50 | J33: =IF($D33=0,"",I33/$D33) | K33: =IF(F33="","",IF(F33<G33,"POR DEBAJO",IF(F33>H33,"POR ENCIMA","EN MERCADO"))) | L33: V | M33: 610 | N33: EXOMA Peptides
A34: FITNESS | B34: BC | C34: BPC-157 | D34: 10 | E34: mg | F34: 1050 | G34: =BANDAS!$E$27*$D34*BANDAS!$E$5*BANDAS!$E$6 | H34: =BANDAS!$F$27*$D34*BANDAS!$E$5*BANDAS!$E$6 | I34: =ROUND(AVERAGE(G34,H34)/50,0)*50 | J34: =IF($D34=0,"",I34/$D34) | K34: =IF(F34="","",IF(F34<G34,"POR DEBAJO",IF(F34>H34,"POR ENCIMA","EN MERCADO"))) | L34: V
A35: FITNESS | B35: BC | C35: BPC-157 | D35: 20 | E35: mg | F35: 1850 | G35: =BANDAS!$E$27*$D35*BANDAS!$E$5*BANDAS!$E$6 | H35: =BANDAS!$F$27*$D35*BANDAS!$E$5*BANDAS!$E$6 | I35: =ROUND(AVERAGE(G35,H35)/50,0)*50 | J35: =IF($D35=0,"",I35/$D35) | K35: =IF(F35="","",IF(F35<G35,"POR DEBAJO",IF(F35>H35,"POR ENCIMA","EN MERCADO"))) | L35: V
A36: FITNESS | B36: BB | C36: BPC-157 + TB-500 | D36: 10 | E36: mg | F36: 2850 | G36: =BANDAS!$E$28*$D36*BANDAS!$E$5*BANDAS!$E$6 | H36: =BANDAS!$F$28*$D36*BANDAS!$E$5*BANDAS!$E$6 | I36: =ROUND(AVERAGE(G36,H36)/50,0)*50 | J36: =IF($D36=0,"",I36/$D36) | K36: =IF(F36="","",IF(F36<G36,"POR DEBAJO",IF(F36>H36,"POR ENCIMA","EN MERCADO"))) | L36: D | M36: 1399 | N36: EXOMA Peptides
A37: FITNESS | B37: BB | C37: BPC-157 + TB-500 | D37: 20 | E37: mg | F37: 3200 | G37: =BANDAS!$E$28*$D37*BANDAS!$E$5*BANDAS!$E$6 | H37: =BANDAS!$F$28*$D37*BANDAS!$E$5*BANDAS!$E$6 | I37: =ROUND(AVERAGE(G37,H37)/50,0)*50 | J37: =IF($D37=0,"",I37/$D37) | K37: =IF(F37="","",IF(F37<G37,"POR DEBAJO",IF(F37>H37,"POR ENCIMA","EN MERCADO"))) | L37: D
A38: FITNESS | B38: CD | C38: CJC-1295 (DAC) | D38: 5 | E38: mg | F38: 1150 | G38: =BANDAS!$E$29*$D38*BANDAS!$E$5*BANDAS!$E$6 | H38: =BANDAS!$F$29*$D38*BANDAS!$E$5*BANDAS!$E$6 | I38: =ROUND(AVERAGE(G38,H38)/50,0)*50 | J38: =IF($D38=0,"",I38/$D38) | K38: =IF(F38="","",IF(F38<G38,"POR DEBAJO",IF(F38>H38,"POR ENCIMA","EN MERCADO"))) | L38: D
A39: FITNESS | B39: CD | C39: CJC-1295 (DAC) | D39: 10 | E39: mg | F39: 2150 | G39: =BANDAS!$E$29*$D39*BANDAS!$E$5*BANDAS!$E$6 | H39: =BANDAS!$F$29*$D39*BANDAS!$E$5*BANDAS!$E$6 | I39: =ROUND(AVERAGE(G39,H39)/50,0)*50 | J39: =IF($D39=0,"",I39/$D39) | K39: =IF(F39="","",IF(F39<G39,"POR DEBAJO",IF(F39>H39,"POR ENCIMA","EN MERCADO"))) | L39: D
A40: FITNESS | B40: CN | C40: CJC-1295 (no DAC) | D40: 5 | E40: mg | F40: 650 | G40: =BANDAS!$E$30*$D40*BANDAS!$E$5*BANDAS!$E$6 | H40: =BANDAS!$F$30*$D40*BANDAS!$E$5*BANDAS!$E$6 | I40: =ROUND(AVERAGE(G40,H40)/50,0)*50 | J40: =IF($D40=0,"",I40/$D40) | K40: =IF(F40="","",IF(F40<G40,"POR DEBAJO",IF(F40>H40,"POR ENCIMA","EN MERCADO"))) | L40: D
A41: FITNESS | B41: CN | C41: CJC-1295 (no DAC) | D41: 10 | E41: mg | F41: 1250 | G41: =BANDAS!$E$30*$D41*BANDAS!$E$5*BANDAS!$E$6 | H41: =BANDAS!$F$30*$D41*BANDAS!$E$5*BANDAS!$E$6 | I41: =ROUND(AVERAGE(G41,H41)/50,0)*50 | J41: =IF($D41=0,"",I41/$D41) | K41: =IF(F41="","",IF(F41<G41,"POR DEBAJO",IF(F41>H41,"POR ENCIMA","EN MERCADO"))) | L41: D
A42: FITNESS | B42: CP | C42: CJC-1295 + Ipamorelin | D42: 10 | E42: mg | F42: 1250 | G42: =BANDAS!$E$31*$D42*BANDAS!$E$5*BANDAS!$E$6 | H42: =BANDAS!$F$31*$D42*BANDAS!$E$5*BANDAS!$E$6 | I42: =ROUND(AVERAGE(G42,H42)/50,0)*50 | J42: =IF($D42=0,"",I42/$D42) | K42: =IF(F42="","",IF(F42<G42,"POR DEBAJO",IF(F42>H42,"POR ENCIMA","EN MERCADO"))) | L42: V
A43: FITNESS | B43: CS | C43: Cagri + Sema | D43: 5 | E43: mg | F43: 750 | G43: =BANDAS!$E$32*$D43*BANDAS!$E$5*BANDAS!$E$6 | H43: =BANDAS!$F$32*$D43*BANDAS!$E$5*BANDAS!$E$6 | I43: =ROUND(AVERAGE(G43,H43)/50,0)*50 | J43: =IF($D43=0,"",I43/$D43) | K43: =IF(F43="","",IF(F43<G43,"POR DEBAJO",IF(F43>H43,"POR ENCIMA","EN MERCADO"))) | L43: D
A44: FITNESS | B44: CS | C44: Cagri + Sema | D44: 10 | E44: mg | F44: 1200 | G44: =BANDAS!$E$32*$D44*BANDAS!$E$5*BANDAS!$E$6 | H44: =BANDAS!$F$32*$D44*BANDAS!$E$5*BANDAS!$E$6 | I44: =ROUND(AVERAGE(G44,H44)/50,0)*50 | J44: =IF($D44=0,"",I44/$D44) | K44: =IF(F44="","",IF(F44<G44,"POR DEBAJO",IF(F44>H44,"POR ENCIMA","EN MERCADO"))) | L44: D
A45: FITNESS | B45: CGL | C45: Cagrilintide | D45: 5 | E45: mg | F45: 900 | G45: =BANDAS!$E$33*$D45*BANDAS!$E$5*BANDAS!$E$6 | H45: =BANDAS!$F$33*$D45*BANDAS!$E$5*BANDAS!$E$6 | I45: =ROUND(AVERAGE(G45,H45)/50,0)*50 | J45: =IF($D45=0,"",I45/$D45) | K45: =IF(F45="","",IF(F45<G45,"POR DEBAJO",IF(F45>H45,"POR ENCIMA","EN MERCADO"))) | L45: D
A46: FITNESS | B46: CGL | C46: Cagrilintide | D46: 10 | E46: mg | F46: 1700 | G46: =BANDAS!$E$33*$D46*BANDAS!$E$5*BANDAS!$E$6 | H46: =BANDAS!$F$33*$D46*BANDAS!$E$5*BANDAS!$E$6 | I46: =ROUND(AVERAGE(G46,H46)/50,0)*50 | J46: =IF($D46=0,"",I46/$D46) | K46: =IF(F46="","",IF(F46<G46,"POR DEBAJO",IF(F46>H46,"POR ENCIMA","EN MERCADO"))) | L46: D
A47: FITNESS | B47: G2 | C47: GHRP-2 | D47: 5 | E47: mg | F47: 500 | G47: =BANDAS!$E$34*$D47*BANDAS!$E$5*BANDAS!$E$6 | H47: =BANDAS!$F$34*$D47*BANDAS!$E$5*BANDAS!$E$6 | I47: =ROUND(AVERAGE(G47,H47)/50,0)*50 | J47: =IF($D47=0,"",I47/$D47) | K47: =IF(F47="","",IF(F47<G47,"POR DEBAJO",IF(F47>H47,"POR ENCIMA","EN MERCADO"))) | L47: D
A48: FITNESS | B48: G2 | C48: GHRP-2 | D48: 10 | E48: mg | F48: 850 | G48: =BANDAS!$E$34*$D48*BANDAS!$E$5*BANDAS!$E$6 | H48: =BANDAS!$F$34*$D48*BANDAS!$E$5*BANDAS!$E$6 | I48: =ROUND(AVERAGE(G48,H48)/50,0)*50 | J48: =IF($D48=0,"",I48/$D48) | K48: =IF(F48="","",IF(F48<G48,"POR DEBAJO",IF(F48>H48,"POR ENCIMA","EN MERCADO"))) | L48: D
A49: FITNESS | B49: G6 | C49: GHRP-6 | D49: 5 | E49: mg | F49: 500 | G49: =BANDAS!$E$35*$D49*BANDAS!$E$5*BANDAS!$E$6 | H49: =BANDAS!$F$35*$D49*BANDAS!$E$5*BANDAS!$E$6 | I49: =ROUND(AVERAGE(G49,H49)/50,0)*50 | J49: =IF($D49=0,"",I49/$D49) | K49: =IF(F49="","",IF(F49<G49,"POR DEBAJO",IF(F49>H49,"POR ENCIMA","EN MERCADO"))) | L49: D
A50: FITNESS | B50: G6 | C50: GHRP-6 | D50: 10 | E50: mg | F50: 850 | G50: =BANDAS!$E$35*$D50*BANDAS!$E$5*BANDAS!$E$6 | H50: =BANDAS!$F$35*$D50*BANDAS!$E$5*BANDAS!$E$6 | I50: =ROUND(AVERAGE(G50,H50)/50,0)*50 | J50: =IF($D50=0,"",I50/$D50) | K50: =IF(F50="","",IF(F50<G50,"POR DEBAJO",IF(F50>H50,"POR ENCIMA","EN MERCADO"))) | L50: D
A51: FITNESS | B51: H | C51: HGH 191AA | D51: 10 | E51: iu | F51: 350 | G51: =BANDAS!$E$36*$D51*BANDAS!$E$5*BANDAS!$E$6 | H51: =BANDAS!$F$36*$D51*BANDAS!$E$5*BANDAS!$E$6 | I51: =ROUND(AVERAGE(G51,H51)/50,0)*50 | J51: =IF($D51=0,"",I51/$D51) | K51: =IF(F51="","",IF(F51<G51,"POR DEBAJO",IF(F51>H51,"POR ENCIMA","EN MERCADO"))) | L51: D
A52: FITNESS | B52: H | C52: HGH 191AA | D52: 12 | E52: iu | F52: 500 | G52: =BANDAS!$E$36*$D52*BANDAS!$E$5*BANDAS!$E$6 | H52: =BANDAS!$F$36*$D52*BANDAS!$E$5*BANDAS!$E$6 | I52: =ROUND(AVERAGE(G52,H52)/50,0)*50 | J52: =IF($D52=0,"",I52/$D52) | K52: =IF(F52="","",IF(F52<G52,"POR DEBAJO",IF(F52>H52,"POR ENCIMA","EN MERCADO"))) | L52: D
A53: FITNESS | B53: H | C53: HGH 191AA | D53: 15 | E53: iu | F53: 750 | G53: =BANDAS!$E$36*$D53*BANDAS!$E$5*BANDAS!$E$6 | H53: =BANDAS!$F$36*$D53*BANDAS!$E$5*BANDAS!$E$6 | I53: =ROUND(AVERAGE(G53,H53)/50,0)*50 | J53: =IF($D53=0,"",I53/$D53) | K53: =IF(F53="","",IF(F53<G53,"POR DEBAJO",IF(F53>H53,"POR ENCIMA","EN MERCADO"))) | L53: D
A54: FITNESS | B54: H | C54: HGH 191AA | D54: 24 | E54: iu | F54: 850 | G54: =BANDAS!$E$36*$D54*BANDAS!$E$5*BANDAS!$E$6 | H54: =BANDAS!$F$36*$D54*BANDAS!$E$5*BANDAS!$E$6 | I54: =ROUND(AVERAGE(G54,H54)/50,0)*50 | J54: =IF($D54=0,"",I54/$D54) | K54: =IF(F54="","",IF(F54<G54,"POR DEBAJO",IF(F54>H54,"POR ENCIMA","EN MERCADO"))) | L54: D
A55: FITNESS | B55: H | C55: HGH 191AA | D55: 36 | E55: iu | F55: 1350 | G55: =BANDAS!$E$36*$D55*BANDAS!$E$5*BANDAS!$E$6 | H55: =BANDAS!$F$36*$D55*BANDAS!$E$5*BANDAS!$E$6 | I55: =ROUND(AVERAGE(G55,H55)/50,0)*50 | J55: =IF($D55=0,"",I55/$D55) | K55: =IF(F55="","",IF(F55<G55,"POR DEBAJO",IF(F55>H55,"POR ENCIMA","EN MERCADO"))) | L55: D
A56: FITNESS | B56: HX | C56: Hexarelin | D56: 2 | E56: mg | F56: 350 | G56: =BANDAS!$E$37*$D56*BANDAS!$E$5*BANDAS!$E$6 | H56: =BANDAS!$F$37*$D56*BANDAS!$E$5*BANDAS!$E$6 | I56: =ROUND(AVERAGE(G56,H56)/50,0)*50 | J56: =IF($D56=0,"",I56/$D56) | K56: =IF(F56="","",IF(F56<G56,"POR DEBAJO",IF(F56>H56,"POR ENCIMA","EN MERCADO"))) | L56: D
A57: FITNESS | B57: HX | C57: Hexarelin | D57: 5 | E57: mg | F57: 850 | G57: =BANDAS!$E$37*$D57*BANDAS!$E$5*BANDAS!$E$6 | H57: =BANDAS!$F$37*$D57*BANDAS!$E$5*BANDAS!$E$6 | I57: =ROUND(AVERAGE(G57,H57)/50,0)*50 | J57: =IF($D57=0,"",I57/$D57) | K57: =IF(F57="","",IF(F57<G57,"POR DEBAJO",IF(F57>H57,"POR ENCIMA","EN MERCADO"))) | L57: D
A58: FITNESS | B58: IG | C58: IGF-1 LR3 | D58: 0.1 | E58: mg | F58: 300 | G58: =BANDAS!$E$38*$D58*BANDAS!$E$5*BANDAS!$E$6 | H58: =BANDAS!$F$38*$D58*BANDAS!$E$5*BANDAS!$E$6 | I58: =ROUND(AVERAGE(G58,H58)/50,0)*50 | J58: =IF($D58=0,"",I58/$D58) | K58: =IF(F58="","",IF(F58<G58,"POR DEBAJO",IF(F58>H58,"POR ENCIMA","EN MERCADO"))) | L58: D
A59: FITNESS | B59: IG | C59: IGF-1 LR3 | D59: 1 | E59: mg | F59: 1350 | G59: =BANDAS!$E$38*$D59*BANDAS!$E$5*BANDAS!$E$6 | H59: =BANDAS!$F$38*$D59*BANDAS!$E$5*BANDAS!$E$6 | I59: =ROUND(AVERAGE(G59,H59)/50,0)*50 | J59: =IF($D59=0,"",I59/$D59) | K59: =IF(F59="","",IF(F59<G59,"POR DEBAJO",IF(F59>H59,"POR ENCIMA","EN MERCADO"))) | L59: D
A60: FITNESS | B60: IPA | C60: Ipamorelin | D60: 5 | E60: mg | F60: 500 | G60: =BANDAS!$E$39*$D60*BANDAS!$E$5*BANDAS!$E$6 | H60: =BANDAS!$F$39*$D60*BANDAS!$E$5*BANDAS!$E$6 | I60: =ROUND(AVERAGE(G60,H60)/50,0)*50 | J60: =IF($D60=0,"",I60/$D60) | K60: =IF(F60="","",IF(F60<G60,"POR DEBAJO",IF(F60>H60,"POR ENCIMA","EN MERCADO"))) | L60: D
A61: FITNESS | B61: IPA | C61: Ipamorelin | D61: 10 | E61: mg | F61: 1000 | G61: =BANDAS!$E$39*$D61*BANDAS!$E$5*BANDAS!$E$6 | H61: =BANDAS!$F$39*$D61*BANDAS!$E$5*BANDAS!$E$6 | I61: =ROUND(AVERAGE(G61,H61)/50,0)*50 | J61: =IF($D61=0,"",I61/$D61) | K61: =IF(F61="","",IF(F61<G61,"POR DEBAJO",IF(F61>H61,"POR ENCIMA","EN MERCADO"))) | L61: D
A62: FITNESS | B62: LC | C62: L-Carnitine | D62: 600 | E62: mg | F62: 750 | G62: =BANDAS!$E$40*$D62*BANDAS!$E$5*BANDAS!$E$6 | H62: =BANDAS!$F$40*$D62*BANDAS!$E$5*BANDAS!$E$6 | I62: =ROUND(AVERAGE(G62,H62)/50,0)*50 | J62: =IF($D62=0,"",I62/$D62) | K62: =IF(F62="","",IF(F62<G62,"POR DEBAJO",IF(F62>H62,"POR ENCIMA","EN MERCADO"))) | L62: D
A63: FITNESS | B63: LC | C63: L-Carnitine | D63: 1200 | E63: mg | F63: 1350 | G63: =BANDAS!$E$40*$D63*BANDAS!$E$5*BANDAS!$E$6 | H63: =BANDAS!$F$40*$D63*BANDAS!$E$5*BANDAS!$E$6 | I63: =ROUND(AVERAGE(G63,H63)/50,0)*50 | J63: =IF($D63=0,"",I63/$D63) | K63: =IF(F63="","",IF(F63<G63,"POR DEBAJO",IF(F63>H63,"POR ENCIMA","EN MERCADO"))) | L63: D
A64: FITNESS | B64: MIC | C64: Lipo-C + B12 | D64: 10 | E64: ml | F64: 6900 | G64: =BANDAS!$E$41*$D64*BANDAS!$E$5*BANDAS!$E$6 | H64: =BANDAS!$F$41*$D64*BANDAS!$E$5*BANDAS!$E$6 | I64: =ROUND(AVERAGE(G64,H64)/50,0)*50 | J64: =IF($D64=0,"",I64/$D64) | K64: =IF(F64="","",IF(F64<G64,"POR DEBAJO",IF(F64>H64,"POR ENCIMA","EN MERCADO"))) | L64: D
A65: FITNESS | B65: MS | C65: MOTS-c | D65: 10 | E65: mg | F65: 850 | G65: =BANDAS!$E$42*$D65*BANDAS!$E$5*BANDAS!$E$6 | H65: =BANDAS!$F$42*$D65*BANDAS!$E$5*BANDAS!$E$6 | I65: =ROUND(AVERAGE(G65,H65)/50,0)*50 | J65: =IF($D65=0,"",I65/$D65) | K65: =IF(F65="","",IF(F65<G65,"POR DEBAJO",IF(F65>H65,"POR ENCIMA","EN MERCADO"))) | L65: D
A66: FITNESS | B66: MS | C66: MOTS-c | D66: 20 | E66: mg | F66: 1600 | G66: =BANDAS!$E$42*$D66*BANDAS!$E$5*BANDAS!$E$6 | H66: =BANDAS!$F$42*$D66*BANDAS!$E$5*BANDAS!$E$6 | I66: =ROUND(AVERAGE(G66,H66)/50,0)*50 | J66: =IF($D66=0,"",I66/$D66) | K66: =IF(F66="","",IF(F66<G66,"POR DEBAJO",IF(F66>H66,"POR ENCIMA","EN MERCADO"))) | L66: D
A67: FITNESS | B67: MS | C67: MOTS-c | D67: 40 | E67: mg | F67: 3200 | G67: =BANDAS!$E$42*$D67*BANDAS!$E$5*BANDAS!$E$6 | H67: =BANDAS!$F$42*$D67*BANDAS!$E$5*BANDAS!$E$6 | I67: =ROUND(AVERAGE(G67,H67)/50,0)*50 | J67: =IF($D67=0,"",I67/$D67) | K67: =IF(F67="","",IF(F67<G67,"POR DEBAJO",IF(F67>H67,"POR ENCIMA","EN MERCADO"))) | L67: D
A68: FITNESS | B68: MZ | C68: Mazdutide | D68: 5 | E68: mg | F68: 750 | G68: =BANDAS!$E$43*$D68*BANDAS!$E$5*BANDAS!$E$6 | H68: =BANDAS!$F$43*$D68*BANDAS!$E$5*BANDAS!$E$6 | I68: =ROUND(AVERAGE(G68,H68)/50,0)*50 | J68: =IF($D68=0,"",I68/$D68) | K68: =IF(F68="","",IF(F68<G68,"POR DEBAJO",IF(F68>H68,"POR ENCIMA","EN MERCADO"))) | L68: D
A69: FITNESS | B69: MZ | C69: Mazdutide | D69: 10 | E69: mg | F69: 1350 | G69: =BANDAS!$E$43*$D69*BANDAS!$E$5*BANDAS!$E$6 | H69: =BANDAS!$F$43*$D69*BANDAS!$E$5*BANDAS!$E$6 | I69: =ROUND(AVERAGE(G69,H69)/50,0)*50 | J69: =IF($D69=0,"",I69/$D69) | K69: =IF(F69="","",IF(F69<G69,"POR DEBAJO",IF(F69>H69,"POR ENCIMA","EN MERCADO"))) | L69: D
A70: FITNESS | B70: RT | C70: Retatrutide | D70: 5 | E70: mg | F70: 850 | G70: =BANDAS!$E$44*$D70*BANDAS!$E$5*BANDAS!$E$6 | H70: =BANDAS!$F$44*$D70*BANDAS!$E$5*BANDAS!$E$6 | I70: =ROUND(AVERAGE(G70,H70)/50,0)*50 | J70: =IF($D70=0,"",I70/$D70) | K70: =IF(F70="","",IF(F70<G70,"POR DEBAJO",IF(F70>H70,"POR ENCIMA","EN MERCADO"))) | L70: V
A71: FITNESS | B71: RT | C71: Retatrutide | D71: 10 | E71: mg | F71: 1650 | G71: =BANDAS!$E$44*$D71*BANDAS!$E$5*BANDAS!$E$6 | H71: =BANDAS!$F$44*$D71*BANDAS!$E$5*BANDAS!$E$6 | I71: =ROUND(AVERAGE(G71,H71)/50,0)*50 | J71: =IF($D71=0,"",I71/$D71) | K71: =IF(F71="","",IF(F71<G71,"POR DEBAJO",IF(F71>H71,"POR ENCIMA","EN MERCADO"))) | L71: V | M71: 960 | N71: exomapeptides.mx
A72: FITNESS | B72: RT | C72: Retatrutide | D72: 15 | E72: mg | F72: 2450 | G72: =BANDAS!$E$44*$D72*BANDAS!$E$5*BANDAS!$E$6 | H72: =BANDAS!$F$44*$D72*BANDAS!$E$5*BANDAS!$E$6 | I72: =ROUND(AVERAGE(G72,H72)/50,0)*50 | J72: =IF($D72=0,"",I72/$D72) | K72: =IF(F72="","",IF(F72<G72,"POR DEBAJO",IF(F72>H72,"POR ENCIMA","EN MERCADO"))) | L72: V
A73: FITNESS | B73: RT | C73: Retatrutide | D73: 20 | E73: mg | F73: 3200 | G73: =BANDAS!$E$44*$D73*BANDAS!$E$5*BANDAS!$E$6 | H73: =BANDAS!$F$44*$D73*BANDAS!$E$5*BANDAS!$E$6 | I73: =ROUND(AVERAGE(G73,H73)/50,0)*50 | J73: =IF($D73=0,"",I73/$D73) | K73: =IF(F73="","",IF(F73<G73,"POR DEBAJO",IF(F73>H73,"POR ENCIMA","EN MERCADO"))) | L73: V
A74: FITNESS | B74: RT | C74: Retatrutide | D74: 30 | E74: mg | F74: 4800 | G74: =BANDAS!$E$44*$D74*BANDAS!$E$5*BANDAS!$E$6 | H74: =BANDAS!$F$44*$D74*BANDAS!$E$5*BANDAS!$E$6 | I74: =ROUND(AVERAGE(G74,H74)/50,0)*50 | J74: =IF($D74=0,"",I74/$D74) | K74: =IF(F74="","",IF(F74<G74,"POR DEBAJO",IF(F74>H74,"POR ENCIMA","EN MERCADO"))) | L74: V
A75: FITNESS | B75: RT | C75: Retatrutide | D75: 40 | E75: mg | F75: 6400 | G75: =BANDAS!$E$44*$D75*BANDAS!$E$5*BANDAS!$E$6 | H75: =BANDAS!$F$44*$D75*BANDAS!$E$5*BANDAS!$E$6 | I75: =ROUND(AVERAGE(G75,H75)/50,0)*50 | J75: =IF($D75=0,"",I75/$D75) | K75: =IF(F75="","",IF(F75<G75,"POR DEBAJO",IF(F75>H75,"POR ENCIMA","EN MERCADO"))) | L75: V
A76: FITNESS | B76: RT | C76: Retatrutide | D76: 50 | E76: mg | F76: 8050 | G76: =BANDAS!$E$44*$D76*BANDAS!$E$5*BANDAS!$E$6 | H76: =BANDAS!$F$44*$D76*BANDAS!$E$5*BANDAS!$E$6 | I76: =ROUND(AVERAGE(G76,H76)/50,0)*50 | J76: =IF($D76=0,"",I76/$D76) | K76: =IF(F76="","",IF(F76<G76,"POR DEBAJO",IF(F76>H76,"POR ENCIMA","EN MERCADO"))) | L76: V
A77: FITNESS | B77: RT | C77: Retatrutide | D77: 60 | E77: mg | F77: 9650 | G77: =BANDAS!$E$44*$D77*BANDAS!$E$5*BANDAS!$E$6 | H77: =BANDAS!$F$44*$D77*BANDAS!$E$5*BANDAS!$E$6 | I77: =ROUND(AVERAGE(G77,H77)/50,0)*50 | J77: =IF($D77=0,"",I77/$D77) | K77: =IF(F77="","",IF(F77<G77,"POR DEBAJO",IF(F77>H77,"POR ENCIMA","EN MERCADO"))) | L77: V
A78: FITNESS | B78: 2S | C78: SS-31 | D78: 10 | E78: mg | F78: 1000 | G78: =BANDAS!$E$45*$D78*BANDAS!$E$5*BANDAS!$E$6 | H78: =BANDAS!$F$45*$D78*BANDAS!$E$5*BANDAS!$E$6 | I78: =ROUND(AVERAGE(G78,H78)/50,0)*50 | J78: =IF($D78=0,"",I78/$D78) | K78: =IF(F78="","",IF(F78<G78,"POR DEBAJO",IF(F78>H78,"POR ENCIMA","EN MERCADO"))) | L78: D
A79: FITNESS | B79: 2S | C79: SS-31 | D79: 50 | E79: mg | F79: 5200 | G79: =BANDAS!$E$45*$D79*BANDAS!$E$5*BANDAS!$E$6 | H79: =BANDAS!$F$45*$D79*BANDAS!$E$5*BANDAS!$E$6 | I79: =ROUND(AVERAGE(G79,H79)/50,0)*50 | J79: =IF($D79=0,"",I79/$D79) | K79: =IF(F79="","",IF(F79<G79,"POR DEBAJO",IF(F79>H79,"POR ENCIMA","EN MERCADO"))) | L79: D
A80: FITNESS | B80: SM | C80: Semaglutide | D80: 5 | E80: mg | F80: 500 | G80: =BANDAS!$E$46*$D80*BANDAS!$E$5*BANDAS!$E$6 | H80: =BANDAS!$F$46*$D80*BANDAS!$E$5*BANDAS!$E$6 | I80: =ROUND(AVERAGE(G80,H80)/50,0)*50 | J80: =IF($D80=0,"",I80/$D80) | K80: =IF(F80="","",IF(F80<G80,"POR DEBAJO",IF(F80>H80,"POR ENCIMA","EN MERCADO"))) | L80: V
A81: FITNESS | B81: SM | C81: Semaglutide | D81: 10 | E81: mg | F81: 1900 | G81: =BANDAS!$E$46*$D81*BANDAS!$E$5*BANDAS!$E$6 | H81: =BANDAS!$F$46*$D81*BANDAS!$E$5*BANDAS!$E$6 | I81: =ROUND(AVERAGE(G81,H81)/50,0)*50 | J81: =IF($D81=0,"",I81/$D81) | K81: =IF(F81="","",IF(F81<G81,"POR DEBAJO",IF(F81>H81,"POR ENCIMA","EN MERCADO"))) | L81: V
A82: FITNESS | B82: SM | C82: Semaglutide | D82: 15 | E82: mg | F82: 2150 | G82: =BANDAS!$E$46*$D82*BANDAS!$E$5*BANDAS!$E$6 | H82: =BANDAS!$F$46*$D82*BANDAS!$E$5*BANDAS!$E$6 | I82: =ROUND(AVERAGE(G82,H82)/50,0)*50 | J82: =IF($D82=0,"",I82/$D82) | K82: =IF(F82="","",IF(F82<G82,"POR DEBAJO",IF(F82>H82,"POR ENCIMA","EN MERCADO"))) | L82: V
A83: FITNESS | B83: SM | C83: Semaglutide | D83: 20 | E83: mg | F83: 3050 | G83: =BANDAS!$E$46*$D83*BANDAS!$E$5*BANDAS!$E$6 | H83: =BANDAS!$F$46*$D83*BANDAS!$E$5*BANDAS!$E$6 | I83: =ROUND(AVERAGE(G83,H83)/50,0)*50 | J83: =IF($D83=0,"",I83/$D83) | K83: =IF(F83="","",IF(F83<G83,"POR DEBAJO",IF(F83>H83,"POR ENCIMA","EN MERCADO"))) | L83: V
A84: FITNESS | B84: SM | C84: Semaglutide | D84: 30 | E84: mg | F84: 3400 | G84: =BANDAS!$E$46*$D84*BANDAS!$E$5*BANDAS!$E$6 | H84: =BANDAS!$F$46*$D84*BANDAS!$E$5*BANDAS!$E$6 | I84: =ROUND(AVERAGE(G84,H84)/50,0)*50 | J84: =IF($D84=0,"",I84/$D84) | K84: =IF(F84="","",IF(F84<G84,"POR DEBAJO",IF(F84>H84,"POR ENCIMA","EN MERCADO"))) | L84: V
A85: FITNESS | B85: SMO | C85: Sermorelin | D85: 5 | E85: mg | F85: 750 | G85: =BANDAS!$E$47*$D85*BANDAS!$E$5*BANDAS!$E$6 | H85: =BANDAS!$F$47*$D85*BANDAS!$E$5*BANDAS!$E$6 | I85: =ROUND(AVERAGE(G85,H85)/50,0)*50 | J85: =IF($D85=0,"",I85/$D85) | K85: =IF(F85="","",IF(F85<G85,"POR DEBAJO",IF(F85>H85,"POR ENCIMA","EN MERCADO"))) | L85: D
A86: FITNESS | B86: SMO | C86: Sermorelin | D86: 10 | E86: mg | F86: 1350 | G86: =BANDAS!$E$47*$D86*BANDAS!$E$5*BANDAS!$E$6 | H86: =BANDAS!$F$47*$D86*BANDAS!$E$5*BANDAS!$E$6 | I86: =ROUND(AVERAGE(G86,H86)/50,0)*50 | J86: =IF($D86=0,"",I86/$D86) | K86: =IF(F86="","",IF(F86<G86,"POR DEBAJO",IF(F86>H86,"POR ENCIMA","EN MERCADO"))) | L86: D
A87: FITNESS | B87: TB | C87: TB-500 | D87: 5 | E87: mg | F87: 600 | G87: =BANDAS!$E$48*$D87*BANDAS!$E$5*BANDAS!$E$6 | H87: =BANDAS!$F$48*$D87*BANDAS!$E$5*BANDAS!$E$6 | I87: =ROUND(AVERAGE(G87,H87)/50,0)*50 | J87: =IF($D87=0,"",I87/$D87) | K87: =IF(F87="","",IF(F87<G87,"POR DEBAJO",IF(F87>H87,"POR ENCIMA","EN MERCADO"))) | L87: V | M87: 1449 | N87: ZELARA
A88: FITNESS | B88: TB | C88: TB-500 | D88: 10 | E88: mg | F88: 900 | G88: =BANDAS!$E$48*$D88*BANDAS!$E$5*BANDAS!$E$6 | H88: =BANDAS!$F$48*$D88*BANDAS!$E$5*BANDAS!$E$6 | I88: =ROUND(AVERAGE(G88,H88)/50,0)*50 | J88: =IF($D88=0,"",I88/$D88) | K88: =IF(F88="","",IF(F88<G88,"POR DEBAJO",IF(F88>H88,"POR ENCIMA","EN MERCADO"))) | L88: V
A89: FITNESS | B89: TSM | C89: Tesamorelin | D89: 5 | E89: mg | F89: 650 | G89: =BANDAS!$E$49*$D89*BANDAS!$E$5*BANDAS!$E$6 | H89: =BANDAS!$F$49*$D89*BANDAS!$E$5*BANDAS!$E$6 | I89: =ROUND(AVERAGE(G89,H89)/50,0)*50 | J89: =IF($D89=0,"",I89/$D89) | K89: =IF(F89="","",IF(F89<G89,"POR DEBAJO",IF(F89>H89,"POR ENCIMA","EN MERCADO"))) | L89: D
A90: FITNESS | B90: TSM | C90: Tesamorelin | D90: 10 | E90: mg | F90: 1250 | G90: =BANDAS!$E$49*$D90*BANDAS!$E$5*BANDAS!$E$6 | H90: =BANDAS!$F$49*$D90*BANDAS!$E$5*BANDAS!$E$6 | I90: =ROUND(AVERAGE(G90,H90)/50,0)*50 | J90: =IF($D90=0,"",I90/$D90) | K90: =IF(F90="","",IF(F90<G90,"POR DEBAJO",IF(F90>H90,"POR ENCIMA","EN MERCADO"))) | L90: D
A91: FITNESS | B91: TSM | C91: Tesamorelin | D91: 20 | E91: mg | F91: 2450 | G91: =BANDAS!$E$49*$D91*BANDAS!$E$5*BANDAS!$E$6 | H91: =BANDAS!$F$49*$D91*BANDAS!$E$5*BANDAS!$E$6 | I91: =ROUND(AVERAGE(G91,H91)/50,0)*50 | J91: =IF($D91=0,"",I91/$D91) | K91: =IF(F91="","",IF(F91<G91,"POR DEBAJO",IF(F91>H91,"POR ENCIMA","EN MERCADO"))) | L91: D
A92: FITNESS | B92: TR | C92: Tirzepatide | D92: 5 | E92: mg | F92: 1150 | G92: =BANDAS!$E$50*$D92*BANDAS!$E$5*BANDAS!$E$6 | H92: =BANDAS!$F$50*$D92*BANDAS!$E$5*BANDAS!$E$6 | I92: =ROUND(AVERAGE(G92,H92)/50,0)*50 | J92: =IF($D92=0,"",I92/$D92) | K92: =IF(F92="","",IF(F92<G92,"POR DEBAJO",IF(F92>H92,"POR ENCIMA","EN MERCADO"))) | L92: V | M92: 750 | N92: referencia MX «desde»
A93: FITNESS | B93: TR | C93: Tirzepatide | D93: 10 | E93: mg | F93: 1400 | G93: =BANDAS!$E$50*$D93*BANDAS!$E$5*BANDAS!$E$6 | H93: =BANDAS!$F$50*$D93*BANDAS!$E$5*BANDAS!$E$6 | I93: =ROUND(AVERAGE(G93,H93)/50,0)*50 | J93: =IF($D93=0,"",I93/$D93) | K93: =IF(F93="","",IF(F93<G93,"POR DEBAJO",IF(F93>H93,"POR ENCIMA","EN MERCADO"))) | L93: V
A94: FITNESS | B94: TR | C94: Tirzepatide | D94: 15 | E94: mg | F94: 1500 | G94: =BANDAS!$E$50*$D94*BANDAS!$E$5*BANDAS!$E$6 | H94: =BANDAS!$F$50*$D94*BANDAS!$E$5*BANDAS!$E$6 | I94: =ROUND(AVERAGE(G94,H94)/50,0)*50 | J94: =IF($D94=0,"",I94/$D94) | K94: =IF(F94="","",IF(F94<G94,"POR DEBAJO",IF(F94>H94,"POR ENCIMA","EN MERCADO"))) | L94: V
A95: FITNESS | B95: TR | C95: Tirzepatide | D95: 20 | E95: mg | F95: 2000 | G95: =BANDAS!$E$50*$D95*BANDAS!$E$5*BANDAS!$E$6 | H95: =BANDAS!$F$50*$D95*BANDAS!$E$5*BANDAS!$E$6 | I95: =ROUND(AVERAGE(G95,H95)/50,0)*50 | J95: =IF($D95=0,"",I95/$D95) | K95: =IF(F95="","",IF(F95<G95,"POR DEBAJO",IF(F95>H95,"POR ENCIMA","EN MERCADO"))) | L95: V
A96: FITNESS | B96: TR | C96: Tirzepatide | D96: 30 | E96: mg | F96: 3100 | G96: =BANDAS!$E$50*$D96*BANDAS!$E$5*BANDAS!$E$6 | H96: =BANDAS!$F$50*$D96*BANDAS!$E$5*BANDAS!$E$6 | I96: =ROUND(AVERAGE(G96,H96)/50,0)*50 | J96: =IF($D96=0,"",I96/$D96) | K96: =IF(F96="","",IF(F96<G96,"POR DEBAJO",IF(F96>H96,"POR ENCIMA","EN MERCADO"))) | L96: V
A97: FITNESS | B97: TR | C97: Tirzepatide | D97: 40 | E97: mg | F97: 4100 | G97: =BANDAS!$E$50*$D97*BANDAS!$E$5*BANDAS!$E$6 | H97: =BANDAS!$F$50*$D97*BANDAS!$E$5*BANDAS!$E$6 | I97: =ROUND(AVERAGE(G97,H97)/50,0)*50 | J97: =IF($D97=0,"",I97/$D97) | K97: =IF(F97="","",IF(F97<G97,"POR DEBAJO",IF(F97>H97,"POR ENCIMA","EN MERCADO"))) | L97: V
A98: FITNESS | B98: TR | C98: Tirzepatide | D98: 50 | E98: mg | F98: 5050 | G98: =BANDAS!$E$50*$D98*BANDAS!$E$5*BANDAS!$E$6 | H98: =BANDAS!$F$50*$D98*BANDAS!$E$5*BANDAS!$E$6 | I98: =ROUND(AVERAGE(G98,H98)/50,0)*50 | J98: =IF($D98=0,"",I98/$D98) | K98: =IF(F98="","",IF(F98<G98,"POR DEBAJO",IF(F98>H98,"POR ENCIMA","EN MERCADO"))) | L98: V
A99: FITNESS | B99: TR | C99: Tirzepatide | D99: 60 | E99: mg | F99: 6050 | G99: =BANDAS!$E$50*$D99*BANDAS!$E$5*BANDAS!$E$6 | H99: =BANDAS!$F$50*$D99*BANDAS!$E$5*BANDAS!$E$6 | I99: =ROUND(AVERAGE(G99,H99)/50,0)*50 | J99: =IF($D99=0,"",I99/$D99) | K99: =IF(F99="","",IF(F99<G99,"POR DEBAJO",IF(F99>H99,"POR ENCIMA","EN MERCADO"))) | L99: V
A100: LONGEVITY | B100: CTL | C100: Cartalax | D100: 20 | E100: mg | F100: 2700 | G100: =BANDAS!$E$51*$D100*BANDAS!$E$5*BANDAS!$E$6 | H100: =BANDAS!$F$51*$D100*BANDAS!$E$5*BANDAS!$E$6 | I100: =ROUND(AVERAGE(G100,H100)/50,0)*50 | J100: =IF($D100=0,"",I100/$D100) | K100: =IF(F100="","",IF(F100<G100,"POR DEBAJO",IF(F100>H100,"POR ENCIMA","EN MERCADO"))) | L100: D
A101: LONGEVITY | B101: DS | C101: DSIP | D101: 5 | E101: mg | F101: 350 | G101: =BANDAS!$E$52*$D101*BANDAS!$E$5*BANDAS!$E$6 | H101: =BANDAS!$F$52*$D101*BANDAS!$E$5*BANDAS!$E$6 | I101: =ROUND(AVERAGE(G101,H101)/50,0)*50 | J101: =IF($D101=0,"",I101/$D101) | K101: =IF(F101="","",IF(F101<G101,"POR DEBAJO",IF(F101>H101,"POR ENCIMA","EN MERCADO"))) | L101: D
A102: LONGEVITY | B102: DS | C102: DSIP | D102: 10 | E102: mg | F102: 850 | G102: =BANDAS!$E$52*$D102*BANDAS!$E$5*BANDAS!$E$6 | H102: =BANDAS!$F$52*$D102*BANDAS!$E$5*BANDAS!$E$6 | I102: =ROUND(AVERAGE(G102,H102)/50,0)*50 | J102: =IF($D102=0,"",I102/$D102) | K102: =IF(F102="","",IF(F102<G102,"POR DEBAJO",IF(F102>H102,"POR ENCIMA","EN MERCADO"))) | L102: D
...

Sheet USA
B2: PEPTIDEX · PRECIOS DE VENTA — USA
B3: Precio de mercado y precio sugerido para las 118 presentaciones. La columna amarilla es la respuesta. 02.08.2026
A5: LÍNEA | B5: CÓDIGO | C5: COMPUESTO | D5: CANT. | E5: UNIDAD | F5: TU PRECIO HOY | G5: MERCADO BAJO | H5: MERCADO ALTO | I5: PRECIO SUGERIDO | J5: PRECIO POR UNIDAD | K5: ¿DÓNDE QUEDAS? | L5: CONF.
A6: BEAUTY | B6: AC | C6: AHK-Cu | D6: 20 | E6: mg | F6: 20 | G6: =BANDAS!$E$9*$D6 | H6: =BANDAS!$F$9*$D6 | I6: =ROUND(AVERAGE(G6,H6)/1,0)*1 | J6: =IF($D6=0,"",I6/$D6) | K6: =IF(F6="","",IF(F6<G6,"POR DEBAJO",IF(F6>H6,"POR ENCIMA","EN MERCADO"))) | L6: D
A7: BEAUTY | B7: AC | C7: AHK-Cu | D7: 50 | E7: mg | F7: 55 | G7: =BANDAS!$E$9*$D7 | H7: =BANDAS!$F$9*$D7 | I7: =ROUND(AVERAGE(G7,H7)/1,0)*1 | J7: =IF($D7=0,"",I7/$D7) | K7: =IF(F7="","",IF(F7<G7,"POR DEBAJO",IF(F7>H7,"POR ENCIMA","EN MERCADO"))) | L7: D
A8: BEAUTY | B8: CU | C8: GHK-Cu | D8: 50 | E8: mg | F8: 35 | G8: =BANDAS!$E$10*$D8 | H8: =BANDAS!$F$10*$D8 | I8: =ROUND(AVERAGE(G8,H8)/1,0)*1 | J8: =IF($D8=0,"",I8/$D8) | K8: =IF(F8="","",IF(F8<G8,"POR DEBAJO",IF(F8>H8,"POR ENCIMA","EN MERCADO"))) | L8: V
A9: BEAUTY | B9: CU | C9: GHK-Cu | D9: 100 | E9: mg | F9: 75 | G9: =BANDAS!$E$10*$D9 | H9: =BANDAS!$F$10*$D9 | I9: =ROUND(AVERAGE(G9,H9)/1,0)*1 | J9: =IF($D9=0,"",I9/$D9) | K9: =IF(F9="","",IF(F9<G9,"POR DEBAJO",IF(F9>H9,"POR ENCIMA","EN MERCADO"))) | L9: V
A10: BEAUTY | B10: GL | C10: GLOW Blend | D10: 70 | E10: mg | F10: 260 | G10: =BANDAS!$E$11*$D10 | H10: =BANDAS!$F$11*$D10 | I10: =ROUND(AVERAGE(G10,H10)/1,0)*1 | J10: =IF($D10=0,"",I10/$D10) | K10: =IF(F10="","",IF(F10<G10,"POR DEBAJO",IF(F10>H10,"POR ENCIMA","EN MERCADO"))) | L10: D
A11: BEAUTY | B11: GT | C11: Glutathione | D11: 600 | E11: mg | F11: 45 | G11: =BANDAS!$E$12*$D11 | H11: =BANDAS!$F$12*$D11 | I11: =ROUND(AVERAGE(G11,H11)/1,0)*1 | J11: =IF($D11=0,"",I11/$D11) | K11: =IF(F11="","",IF(F11<G11,"POR DEBAJO",IF(F11>H11,"POR ENCIMA","EN MERCADO"))) | L11: D
A12: BEAUTY | B12: GT | C12: Glutathione | D12: 1500 | E12: mg | F12: 110 | G12: =BANDAS!$E$12*$D12 | H12: =BANDAS!$F$12*$D12 | I12: =ROUND(AVERAGE(G12,H12)/1,0)*1 | J12: =IF($D12=0,"",I12/$D12) | K12: =IF(F12="","",IF(F12<G12,"POR DEBAJO",IF(F12>H12,"POR ENCIMA","EN MERCADO"))) | L12: D
A13: BEAUTY | B13: KL | C13: KLOW Blend | D13: 80 | E13: mg | F13: 300 | G13: =BANDAS!$E$13*$D13 | H13: =BANDAS!$F$13*$D13 | I13: =ROUND(AVERAGE(G13,H13)/1,0)*1 | J13: =IF($D13=0,"",I13/$D13) | K13: =IF(F13="","",IF(F13<G13,"POR DEBAJO",IF(F13>H13,"POR ENCIMA","EN MERCADO"))) | L13: D
A14: BEAUTY | B14: KP | C14: KPV | D14: 5 | E14: mg | F14: 20 | G14: =BANDAS!$E$14*$D14 | H14: =BANDAS!$F$14*$D14 | I14: =ROUND(AVERAGE(G14,H14)/1,0)*1 | J14: =IF($D14=0,"",I14/$D14) | K14: =IF(F14="","",IF(F14<G14,"POR DEBAJO",IF(F14>H14,"POR ENCIMA","EN MERCADO"))) | L14: D
A15: BEAUTY | B15: KP | C15: KPV | D15: 10 | E15: mg | F15: 35 | G15: =BANDAS!$E$14*$D15 | H15: =BANDAS!$F$14*$D15 | I15: =ROUND(AVERAGE(G15,H15)/1,0)*1 | J15: =IF($D15=0,"",I15/$D15) | K15: =IF(F15="","",IF(F15<G15,"POR DEBAJO",IF(F15>H15,"POR ENCIMA","EN MERCADO"))) | L15: D
A16: BEAUTY | B16: MX | C16: Matrixyl | D16: 10 | E16: mg | F16: 85 | G16: =BANDAS!$E$15*$D16 | H16: =BANDAS!$F$15*$D16 | I16: =ROUND(AVERAGE(G16,H16)/1,0)*1 | J16: =IF($D16=0,"",I16/$D16) | K16: =IF(F16="","",IF(F16<G16,"POR DEBAJO",IF(F16>H16,"POR ENCIMA","EN MERCADO"))) | L16: D
A17: BEAUTY | B17: MT1 | C17: Melanotan I | D17: 10 | E17: mg | F17: 40 | G17: =BANDAS!$E$16*$D17 | H17: =BANDAS!$F$16*$D17 | I17: =ROUND(AVERAGE(G17,H17)/1,0)*1 | J17: =IF($D17=0,"",I17/$D17) | K17: =IF(F17="","",IF(F17<G17,"POR DEBAJO",IF(F17>H17,"POR ENCIMA","EN MERCADO"))) | L17: D
A18: BEAUTY | B18: MT2 | C18: Melanotan II | D18: 10 | E18: mg | F18: 40 | G18: =BANDAS!$E$17*$D18 | H18: =BANDAS!$F$17*$D18 | I18: =ROUND(AVERAGE(G18,H18)/1,0)*1 | J18: =IF($D18=0,"",I18/$D18) | K18: =IF(F18="","",IF(F18<G18,"POR DEBAJO",IF(F18>H18,"POR ENCIMA","EN MERCADO"))) | L18: V
A19: BEAUTY | B19: OT | C19: Oxytocin | D19: 5 | E19: mg | F19: 40 | G19: =BANDAS!$E$18*$D19 | H19: =BANDAS!$F$18*$D19 | I19: =ROUND(AVERAGE(G19,H19)/1,0)*1 | J19: =IF($D19=0,"",I19/$D19) | K19: =IF(F19="","",IF(F19<G19,"POR DEBAJO",IF(F19>H19,"POR ENCIMA","EN MERCADO"))) | L19: D
A20: BEAUTY | B20: PT | C20: PT-141 | D20: 10 | E20: mg | F20: 40 | G20: =BANDAS!$E$19*$D20 | H20: =BANDAS!$F$19*$D20 | I20: =ROUND(AVERAGE(G20,H20)/1,0)*1 | J20: =IF($D20=0,"",I20/$D20) | K20: =IF(F20="","",IF(F20<G20,"POR DEBAJO",IF(F20>H20,"POR ENCIMA","EN MERCADO"))) | L20: V
A21: BEAUTY | B21: NP8 | C21: Snap-8 | D21: 10 | E21: mg | F21: 35 | G21: =BANDAS!$E$20*$D21 | H21: =BANDAS!$F$20*$D21 | I21: =ROUND(AVERAGE(G21,H21)/1,0)*1 | J21: =IF($D21=0,"",I21/$D21) | K21: =IF(F21="","",IF(F21<G21,"POR DEBAJO",IF(F21>H21,"POR ENCIMA","EN MERCADO"))) | L21: D
A22: FITNESS | B22: AM | C22: 5-Amino-1MQ | D22: 5 | E22: mg | F22: 12 | G22: =BANDAS!$E$21*$D22 | H22: =BANDAS!$F$21*$D22 | I22: =ROUND(AVERAGE(G22,H22)/1,0)*1 | J22: =IF($D22=0,"",I22/$D22) | K22: =IF(F22="","",IF(F22<G22,"POR DEBAJO",IF(F22>H22,"POR ENCIMA","EN MERCADO"))) | L22: D
A23: FITNESS | B23: AM | C23: 5-Amino-1MQ | D23: 10 | E23: mg | F23: 21 | G23: =BANDAS!$E$21*$D23 | H23: =BANDAS!$F$21*$D23 | I23: =ROUND(AVERAGE(G23,H23)/1,0)*1 | J23: =IF($D23=0,"",I23/$D23) | K23: =IF(F23="","",IF(F23<G23,"POR DEBAJO",IF(F23>H23,"POR ENCIMA","EN MERCADO"))) | L23: D
A24: FITNESS | B24: AM | C24: 5-Amino-1MQ | D24: 50 | E24: mg | F24: 95 | G24: =BANDAS!$E$21*$D24 | H24: =BANDAS!$F$21*$D24 | I24: =ROUND(AVERAGE(G24,H24)/1,0)*1 | J24: =IF($D24=0,"",I24/$D24) | K24: =IF(F24="","",IF(F24<G24,"POR DEBAJO",IF(F24>H24,"POR ENCIMA","EN MERCADO"))) | L24: D
A25: FITNESS | B25: AR | C25: AICAR | D25: 50 | E25: mg | F25: 55 | G25: =BANDAS!$E$22*$D25 | H25: =BANDAS!$F$22*$D25 | I25: =ROUND(AVERAGE(G25,H25)/1,0)*1 | J25: =IF($D25=0,"",I25/$D25) | K25: =IF(F25="","",IF(F25<G25,"POR DEBAJO",IF(F25>H25,"POR ENCIMA","EN MERCADO"))) | L25: D
A26: FITNESS | B26: AR | C26: AICAR | D26: 100 | E26: mg | F26: 110 | G26: =BANDAS!$E$22*$D26 | H26: =BANDAS!$F$22*$D26 | I26: =ROUND(AVERAGE(G26,H26)/1,0)*1 | J26: =IF($D26=0,"",I26/$D26) | K26: =IF(F26="","",IF(F26<G26,"POR DEBAJO",IF(F26>H26,"POR ENCIMA","EN MERCADO"))) | L26: D
A27: FITNESS | B27: AD | C27: AOD-9604 | D27: 5 | E27: mg | F27: 31 | G27: =BANDAS!$E$23*$D27 | H27: =BANDAS!$F$23*$D27 | I27: =ROUND(AVERAGE(G27,H27)/1,0)*1 | J27: =IF($D27=0,"",I27/$D27) | K27: =IF(F27="","",IF(F27<G27,"POR DEBAJO",IF(F27>H27,"POR ENCIMA","EN MERCADO"))) | L27: D
A28: FITNESS | B28: AD | C28: AOD-9604 | D28: 10 | E28: mg | F28: 56 | G28: =BANDAS!$E$23*$D28 | H28: =BANDAS!$F$23*$D28 | I28: =ROUND(AVERAGE(G28,H28)/1,0)*1 | J28: =IF($D28=0,"",I28/$D28) | K28: =IF(F28="","",IF(F28<G28,"POR DEBAJO",IF(F28>H28,"POR ENCIMA","EN MERCADO"))) | L28: D
A29: FITNESS | B29: AX | C29: Adamax | D29: 10 | E29: mg | F29: 85 | G29: =BANDAS!$E$24*$D29 | H29: =BANDAS!$F$24*$D29 | I29: =ROUND(AVERAGE(G29,H29)/1,0)*1 | J29: =IF($D29=0,"",I29/$D29) | K29: =IF(F29="","",IF(F29<G29,"POR DEBAJO",IF(F29>H29,"POR ENCIMA","EN MERCADO"))) | L29: D
A30: FITNESS | B30: APT | C30: Adipotide | D30: 5 | E30: mg | F30: 40 | G30: =BANDAS!$E$25*$D30 | H30: =BANDAS!$F$25*$D30 | I30: =ROUND(AVERAGE(G30,H30)/1,0)*1 | J30: =IF($D30=0,"",I30/$D30) | K30: =IF(F30="","",IF(F30<G30,"POR DEBAJO",IF(F30>H30,"POR ENCIMA","EN MERCADO"))) | L30: D
A31: FITNESS | B31: APT | C31: Adipotide | D31: 10 | E31: mg | F31: 85 | G31: =BANDAS!$E$25*$D31 | H31: =BANDAS!$F$25*$D31 | I31: =ROUND(AVERAGE(G31,H31)/1,0)*1 | J31: =IF($D31=0,"",I31/$D31) | K31: =IF(F31="","",IF(F31<G31,"POR DEBAJO",IF(F31>H31,"POR ENCIMA","EN MERCADO"))) | L31: D
A32: FITNESS | B32: RA | C32: Ara-290 | D32: 10 | E32: mg | F32: 85 | G32: =BANDAS!$E$26*$D32 | H32: =BANDAS!$F$26*$D32 | I32: =ROUND(AVERAGE(G32,H32)/1,0)*1 | J32: =IF($D32=0,"",I32/$D32) | K32: =IF(F32="","",IF(F32<G32,"POR DEBAJO",IF(F32>H32,"POR ENCIMA","EN MERCADO"))) | L32: D
A33: FITNESS | B33: BC | C33: BPC-157 | D33: 5 | E33: mg | F33: 20 | G33: =BANDAS!$E$27*$D33 | H33: =BANDAS!$F$27*$D33 | I33: =ROUND(AVERAGE(G33,H33)/1,0)*1 | J33: =IF($D33=0,"",I33/$D33) | K33: =IF(F33="","",IF(F33<G33,"POR DEBAJO",IF(F33>H33,"POR ENCIMA","EN MERCADO"))) | L33: V
A34: FITNESS | B34: BC | C34: BPC-157 | D34: 10 | E34: mg | F34: 35 | G34: =BANDAS!$E$27*$D34 | H34: =BANDAS!$F$27*$D34 | I34: =ROUND(AVERAGE(G34,H34)/1,0)*1 | J34: =IF($D34=0,"",I34/$D34) | K34: =IF(F34="","",IF(F34<G34,"POR DEBAJO",IF(F34>H34,"POR ENCIMA","EN MERCADO"))) | L34: V
A35: FITNESS | B35: BC | C35: BPC-157 | D35: 20 | E35: mg | F35: 75 | G35: =BANDAS!$E$27*$D35 | H35: =BANDAS!$F$27*$D35 | I35: =ROUND(AVERAGE(G35,H35)/1,0)*1 | J35: =IF($D35=0,"",I35/$D35) | K35: =IF(F35="","",IF(F35<G35,"POR DEBAJO",IF(F35>H35,"POR ENCIMA","EN MERCADO"))) | L35: V
A36: FITNESS | B36: BB | C36: BPC-157 + TB-500 | D36: 10 | E36: mg | F36: 35 | G36: =BANDAS!$E$28*$D36 | H36: =BANDAS!$F$28*$D36 | I36: =ROUND(AVERAGE(G36,H36)/1,0)*1 | J36: =IF($D36=0,"",I36/$D36) | K36: =IF(F36="","",IF(F36<G36,"POR DEBAJO",IF(F36>H36,"POR ENCIMA","EN MERCADO"))) | L36: D
A37: FITNESS | B37: BB | C37: BPC-157 + TB-500 | D37: 20 | E37: mg | F37: 75 | G37: =BANDAS!$E$28*$D37 | H37: =BANDAS!$F$28*$D37 | I37: =ROUND(AVERAGE(G37,H37)/1,0)*1 | J37: =IF($D37=0,"",I37/$D37) | K37: =IF(F37="","",IF(F37<G37,"POR DEBAJO",IF(F37>H37,"POR ENCIMA","EN MERCADO"))) | L37: D
A38: FITNESS | B38: CD | C38: CJC-1295 (DAC) | D38: 5 | E38: mg | F38: 44 | G38: =BANDAS!$E$29*$D38 | H38: =BANDAS!$F$29*$D38 | I38: =ROUND(AVERAGE(G38,H38)/1,0)*1 | J38: =IF($D38=0,"",I38/$D38) | K38: =IF(F38="","",IF(F38<G38,"POR DEBAJO",IF(F38>H38,"POR ENCIMA","EN MERCADO"))) | L38: D
A39: FITNESS | B39: CD | C39: CJC-1295 (DAC) | D39: 10 | E39: mg | F39: 82 | G39: =BANDAS!$E$29*$D39 | H39: =BANDAS!$F$29*$D39 | I39: =ROUND(AVERAGE(G39,H39)/1,0)*1 | J39: =IF($D39=0,"",I39/$D39) | K39: =IF(F39="","",IF(F39<G39,"POR DEBAJO",IF(F39>H39,"POR ENCIMA","EN MERCADO"))) | L39: D
A40: FITNESS | B40: CN | C40: CJC-1295 (no DAC) | D40: 5 | E40: mg | F40: 25 | G40: =BANDAS!$E$30*$D40 | H40: =BANDAS!$F$30*$D40 | I40: =ROUND(AVERAGE(G40,H40)/1,0)*1 | J40: =IF($D40=0,"",I40/$D40) | K40: =IF(F40="","",IF(F40<G40,"POR DEBAJO",IF(F40>H40,"POR ENCIMA","EN MERCADO"))) | L40: D
A41: FITNESS | B41: CN | C41: CJC-1295 (no DAC) | D41: 10 | E41: mg | F41: 50 | G41: =BANDAS!$E$30*$D41 | H41: =BANDAS!$F$30*$D41 | I41: =ROUND(AVERAGE(G41,H41)/1,0)*1 | J41: =IF($D41=0,"",I41/$D41) | K41: =IF(F41="","",IF(F41<G41,"POR DEBAJO",IF(F41>H41,"POR ENCIMA","EN MERCADO"))) | L41: D
A42: FITNESS | B42: CP | C42: CJC-1295 + Ipamorelin | D42: 10 | E42: mg | F42: 50 | G42: =BANDAS!$E$31*$D42 | H42: =BANDAS!$F$31*$D42 | I42: =ROUND(AVERAGE(G42,H42)/1,0)*1 | J42: =IF($D42=0,"",I42/$D42) | K42: =IF(F42="","",IF(F42<G42,"POR DEBAJO",IF(F42>H42,"POR ENCIMA","EN MERCADO"))) | L42: V
A43: FITNESS | B43: CS | C43: Cagri + Sema | D43: 5 | E43: mg | F43: 29 | G43: =BANDAS!$E$32*$D43 | H43: =BANDAS!$F$32*$D43 | I43: =ROUND(AVERAGE(G43,H43)/1,0)*1 | J43: =IF($D43=0,"",I43/$D43) | K43: =IF(F43="","",IF(F43<G43,"POR DEBAJO",IF(F43>H43,"POR ENCIMA","EN MERCADO"))) | L43: D
A44: FITNESS | B44: CS | C44: Cagri + Sema | D44: 10 | E44: mg | F44: 46 | G44: =BANDAS!$E$32*$D44 | H44: =BANDAS!$F$32*$D44 | I44: =ROUND(AVERAGE(G44,H44)/1,0)*1 | J44: =IF($D44=0,"",I44/$D44) | K44: =IF(F44="","",IF(F44<G44,"POR DEBAJO",IF(F44>H44,"POR ENCIMA","EN MERCADO"))) | L44: D
A45: FITNESS | B45: CGL | C45: Cagrilintide | D45: 5 | E45: mg | F45: 33 | G45: =BANDAS!$E$33*$D45 | H45: =BANDAS!$F$33*$D45 | I45: =ROUND(AVERAGE(G45,H45)/1,0)*1 | J45: =IF($D45=0,"",I45/$D45) | K45: =IF(F45="","",IF(F45<G45,"POR DEBAJO",IF(F45>H45,"POR ENCIMA","EN MERCADO"))) | L45: D
A46: FITNESS | B46: CGL | C46: Cagrilintide | D46: 10 | E46: mg | F46: 64 | G46: =BANDAS!$E$33*$D46 | H46: =BANDAS!$F$33*$D46 | I46: =ROUND(AVERAGE(G46,H46)/1,0)*1 | J46: =IF($D46=0,"",I46/$D46) | K46: =IF(F46="","",IF(F46<G46,"POR DEBAJO",IF(F46>H46,"POR ENCIMA","EN MERCADO"))) | L46: D
A47: FITNESS | B47: G2 | C47: GHRP-2 | D47: 5 | E47: mg | F47: 20 | G47: =BANDAS!$E$34*$D47 | H47: =BANDAS!$F$34*$D47 | I47: =ROUND(AVERAGE(G47,H47)/1,0)*1 | J47: =IF($D47=0,"",I47/$D47) | K47: =IF(F47="","",IF(F47<G47,"POR DEBAJO",IF(F47>H47,"POR ENCIMA","EN MERCADO"))) | L47: D
A48: FITNESS | B48: G2 | C48: GHRP-2 | D48: 10 | E48: mg | F48: 35 | G48: =BANDAS!$E$34*$D48 | H48: =BANDAS!$F$34*$D48 | I48: =ROUND(AVERAGE(G48,H48)/1,0)*1 | J48: =IF($D48=0,"",I48/$D48) | K48: =IF(F48="","",IF(F48<G48,"POR DEBAJO",IF(F48>H48,"POR ENCIMA","EN MERCADO"))) | L48: D
A49: FITNESS | B49: G6 | C49: GHRP-6 | D49: 5 | E49: mg | F49: 20 | G49: =BANDAS!$E$35*$D49 | H49: =BANDAS!$F$35*$D49 | I49: =ROUND(AVERAGE(G49,H49)/1,0)*1 | J49: =IF($D49=0,"",I49/$D49) | K49: =IF(F49="","",IF(F49<G49,"POR DEBAJO",IF(F49>H49,"POR ENCIMA","EN MERCADO"))) | L49: D
A50: FITNESS | B50: G6 | C50: GHRP-6 | D50: 10 | E50: mg | F50: 35 | G50: =BANDAS!$E$35*$D50 | H50: =BANDAS!$F$35*$D50 | I50: =ROUND(AVERAGE(G50,H50)/1,0)*1 | J50: =IF($D50=0,"",I50/$D50) | K50: =IF(F50="","",IF(F50<G50,"POR DEBAJO",IF(F50>H50,"POR ENCIMA","EN MERCADO"))) | L50: D
A51: FITNESS | B51: H | C51: HGH 191AA | D51: 10 | E51: iu | F51: 15 | G51: =BANDAS!$E$36*$D51 | H51: =BANDAS!$F$36*$D51 | I51: =ROUND(AVERAGE(G51,H51)/1,0)*1 | J51: =IF($D51=0,"",I51/$D51) | K51: =IF(F51="","",IF(F51<G51,"POR DEBAJO",IF(F51>H51,"POR ENCIMA","EN MERCADO"))) | L51: D
A52: FITNESS | B52: H | C52: HGH 191AA | D52: 12 | E52: iu | F52: 20 | G52: =BANDAS!$E$36*$D52 | H52: =BANDAS!$F$36*$D52 | I52: =ROUND(AVERAGE(G52,H52)/1,0)*1 | J52: =IF($D52=0,"",I52/$D52) | K52: =IF(F52="","",IF(F52<G52,"POR DEBAJO",IF(F52>H52,"POR ENCIMA","EN MERCADO"))) | L52: D
A53: FITNESS | B53: H | C53: HGH 191AA | D53: 15 | E53: iu | F53: 30 | G53: =BANDAS!$E$36*$D53 | H53: =BANDAS!$F$36*$D53 | I53: =ROUND(AVERAGE(G53,H53)/1,0)*1 | J53: =IF($D53=0,"",I53/$D53) | K53: =IF(F53="","",IF(F53<G53,"POR DEBAJO",IF(F53>H53,"POR ENCIMA","EN MERCADO"))) | L53: D
A54: FITNESS | B54: H | C54: HGH 191AA | D54: 24 | E54: iu | F54: 35 | G54: =BANDAS!$E$36*$D54 | H54: =BANDAS!$F$36*$D54 | I54: =ROUND(AVERAGE(G54,H54)/1,0)*1 | J54: =IF($D54=0,"",I54/$D54) | K54: =IF(F54="","",IF(F54<G54,"POR DEBAJO",IF(F54>H54,"POR ENCIMA","EN MERCADO"))) | L54: D
A55: FITNESS | B55: H | C55: HGH 191AA | D55: 36 | E55: iu | F55: 55 | G55: =BANDAS!$E$36*$D55 | H55: =BANDAS!$F$36*$D55 | I55: =ROUND(AVERAGE(G55,H55)/1,0)*1 | J55: =IF($D55=0,"",I55/$D55) | K55: =IF(F55="","",IF(F55<G55,"POR DEBAJO",IF(F55>H55,"POR ENCIMA","EN MERCADO"))) | L55: D
A56: FITNESS | B56: HX | C56: Hexarelin | D56: 2 | E56: mg | F56: 15 | G56: =BANDAS!$E$37*$D56 | H56: =BANDAS!$F$37*$D56 | I56: =ROUND(AVERAGE(G56,H56)/1,0)*1 | J56: =IF($D56=0,"",I56/$D56) | K56: =IF(F56="","",IF(F56<G56,"POR DEBAJO",IF(F56>H56,"POR ENCIMA","EN MERCADO"))) | L56: D
A57: FITNESS | B57: HX | C57: Hexarelin | D57: 5 | E57: mg | F57: 35 | G57: =BANDAS!$E$37*$D57 | H57: =BANDAS!$F$37*$D57 | I57: =ROUND(AVERAGE(G57,H57)/1,0)*1 | J57: =IF($D57=0,"",I57/$D57) | K57: =IF(F57="","",IF(F57<G57,"POR DEBAJO",IF(F57>H57,"POR ENCIMA","EN MERCADO"))) | L57: D
A58: FITNESS | B58: IG | C58: IGF-1 LR3 | D58: 0.1 | E58: mg | F58: 10 | G58: =BANDAS!$E$38*$D58 | H58: =BANDAS!$F$38*$D58 | I58: =ROUND(AVERAGE(G58,H58)/1,0)*1 | J58: =IF($D58=0,"",I58/$D58) | K58: =IF(F58="","",IF(F58<G58,"POR DEBAJO",IF(F58>H58,"POR ENCIMA","EN MERCADO"))) | L58: D
A59: FITNESS | B59: IG | C59: IGF-1 LR3 | D59: 1 | E59: mg | F59: 51 | G59: =BANDAS!$E$38*$D59 | H59: =BANDAS!$F$38*$D59 | I59: =ROUND(AVERAGE(G59,H59)/1,0)*1 | J59: =IF($D59=0,"",I59/$D59) | K59: =IF(F59="","",IF(F59<G59,"POR DEBAJO",IF(F59>H59,"POR ENCIMA","EN MERCADO"))) | L59: D
A60: FITNESS | B60: IPA | C60: Ipamorelin | D60: 5 | E60: mg | F60: 20 | G60: =BANDAS!$E$39*$D60 | H60: =BANDAS!$F$39*$D60 | I60: =ROUND(AVERAGE(G60,H60)/1,0)*1 | J60: =IF($D60=0,"",I60/$D60) | K60: =IF(F60="","",IF(F60<G60,"POR DEBAJO",IF(F60>H60,"POR ENCIMA","EN MERCADO"))) | L60: D
A61: FITNESS | B61: IPA | C61: Ipamorelin | D61: 10 | E61: mg | F61: 40 | G61: =BANDAS!$E$39*$D61 | H61: =BANDAS!$F$39*$D61 | I61: =ROUND(AVERAGE(G61,H61)/1,0)*1 | J61: =IF($D61=0,"",I61/$D61) | K61: =IF(F61="","",IF(F61<G61,"POR DEBAJO",IF(F61>H61,"POR ENCIMA","EN MERCADO"))) | L61: D
A62: FITNESS | B62: LC | C62: L-Carnitine | D62: 600 | E62: mg | F62: 30 | G62: =BANDAS!$E$40*$D62 | H62: =BANDAS!$F$40*$D62 | I62: =ROUND(AVERAGE(G62,H62)/1,0)*1 | J62: =IF($D62=0,"",I62/$D62) | K62: =IF(F62="","",IF(F62<G62,"POR DEBAJO",IF(F62>H62,"POR ENCIMA","EN MERCADO"))) | L62: D
A63: FITNESS | B63: LC | C63: L-Carnitine | D63: 1200 | E63: mg | F63: 55 | G63: =BANDAS!$E$40*$D63 | H63: =BANDAS!$F$40*$D63 | I63: =ROUND(AVERAGE(G63,H63)/1,0)*1 | J63: =IF($D63=0,"",I63/$D63) | K63: =IF(F63="","",IF(F63<G63,"POR DEBAJO",IF(F63>H63,"POR ENCIMA","EN MERCADO"))) | L63: D
A64: FITNESS | B64: MIC | C64: Lipo-C + B12 | D64: 10 | E64: ml | F64: 280 | G64: =BANDAS!$E$41*$D64 | H64: =BANDAS!$F$41*$D64 | I64: =ROUND(AVERAGE(G64,H64)/1,0)*1 | J64: =IF($D64=0,"",I64/$D64) | K64: =IF(F64="","",IF(F64<G64,"POR DEBAJO",IF(F64>H64,"POR ENCIMA","EN MERCADO"))) | L64: D
A65: FITNESS | B65: MS | C65: MOTS-c | D65: 10 | E65: mg | F65: 35 | G65: =BANDAS!$E$42*$D65 | H65: =BANDAS!$F$42*$D65 | I65: =ROUND(AVERAGE(G65,H65)/1,0)*1 | J65: =IF($D65=0,"",I65/$D65) | K65: =IF(F65="","",IF(F65<G65,"POR DEBAJO",IF(F65>H65,"POR ENCIMA","EN MERCADO"))) | L65: D
A66: FITNESS | B66: MS | C66: MOTS-c | D66: 20 | E66: mg | F66: 65 | G66: =BANDAS!$E$42*$D66 | H66: =BANDAS!$F$42*$D66 | I66: =ROUND(AVERAGE(G66,H66)/1,0)*1 | J66: =IF($D66=0,"",I66/$D66) | K66: =IF(F66="","",IF(F66<G66,"POR DEBAJO",IF(F66>H66,"POR ENCIMA","EN MERCADO"))) | L66: D
A67: FITNESS | B67: MS | C67: MOTS-c | D67: 40 | E67: mg | F67: 130 | G67: =BANDAS!$E$42*$D67 | H67: =BANDAS!$F$42*$D67 | I67: =ROUND(AVERAGE(G67,H67)/1,0)*1 | J67: =IF($D67=0,"",I67/$D67) | K67: =IF(F67="","",IF(F67<G67,"POR DEBAJO",IF(F67>H67,"POR ENCIMA","EN MERCADO"))) | L67: D
A68: FITNESS | B68: MZ | C68: Mazdutide | D68: 5 | E68: mg | F68: 28 | G68: =BANDAS!$E$43*$D68 | H68: =BANDAS!$F$43*$D68 | I68: =ROUND(AVERAGE(G68,H68)/1,0)*1 | J68: =IF($D68=0,"",I68/$D68) | K68: =IF(F68="","",IF(F68<G68,"POR DEBAJO",IF(F68>H68,"POR ENCIMA","EN MERCADO"))) | L68: D
A69: FITNESS | B69: MZ | C69: Mazdutide | D69: 10 | E69: mg | F69: 52 | G69: =BANDAS!$E$43*$D69 | H69: =BANDAS!$F$43*$D69 | I69: =ROUND(AVERAGE(G69,H69)/1,0)*1 | J69: =IF($D69=0,"",I69/$D69) | K69: =IF(F69="","",IF(F69<G69,"POR DEBAJO",IF(F69>H69,"POR ENCIMA","EN MERCADO"))) | L69: D
A70: FITNESS | B70: RT | C70: Retatrutide | D70: 5 | E70: mg | F70: 35 | G70: =BANDAS!$E$44*$D70 | H70: =BANDAS!$F$44*$D70 | I70: =ROUND(AVERAGE(G70,H70)/1,0)*1 | J70: =IF($D70=0,"",I70/$D70) | K70: =IF(F70="","",IF(F70<G70,"POR DEBAJO",IF(F70>H70,"POR ENCIMA","EN MERCADO"))) | L70: V
A71: FITNESS | B71: RT | C71: Retatrutide | D71: 10 | E71: mg | F71: 65 | G71: =BANDAS!$E$44*$D71 | H71: =BANDAS!$F$44*$D71 | I71: =ROUND(AVERAGE(G71,H71)/1,0)*1 | J71: =IF($D71=0,"",I71/$D71) | K71: =IF(F71="","",IF(F71<G71,"POR DEBAJO",IF(F71>H71,"POR ENCIMA","EN MERCADO"))) | L71: V
A72: FITNESS | B72: RT | C72: Retatrutide | D72: 15 | E72: mg | F72: 100 | G72: =BANDAS!$E$44*$D72 | H72: =BANDAS!$F$44*$D72 | I72: =ROUND(AVERAGE(G72,H72)/1,0)*1 | J72: =IF($D72=0,"",I72/$D72) | K72: =IF(F72="","",IF(F72<G72,"POR DEBAJO",IF(F72>H72,"POR ENCIMA","EN MERCADO"))) | L72: V
A73: FITNESS | B73: RT | C73: Retatrutide | D73: 20 | E73: mg | F73: 130 | G73: =BANDAS!$E$44*$D73 | H73: =BANDAS!$F$44*$D73 | I73: =ROUND(AVERAGE(G73,H73)/1,0)*1 | J73: =IF($D73=0,"",I73/$D73) | K73: =IF(F73="","",IF(F73<G73,"POR DEBAJO",IF(F73>H73,"POR ENCIMA","EN MERCADO"))) | L73: V
A74: FITNESS | B74: RT | C74: Retatrutide | D74: 30 | E74: mg | F74: 195 | G74: =BANDAS!$E$44*$D74 | H74: =BANDAS!$F$44*$D74 | I74: =ROUND(AVERAGE(G74,H74)/1,0)*1 | J74: =IF($D74=0,"",I74/$D74) | K74: =IF(F74="","",IF(F74<G74,"POR DEBAJO",IF(F74>H74,"POR ENCIMA","EN MERCADO"))) | L74: V
A75: FITNESS | B75: RT | C75: Retatrutide | D75: 40 | E75: mg | F75: 260 | G75: =BANDAS!$E$44*$D75 | H75: =BANDAS!$F$44*$D75 | I75: =ROUND(AVERAGE(G75,H75)/1,0)*1 | J75: =IF($D75=0,"",I75/$D75) | K75: =IF(F75="","",IF(F75<G75,"POR DEBAJO",IF(F75>H75,"POR ENCIMA","EN MERCADO"))) | L75: V
A76: FITNESS | B76: RT | C76: Retatrutide | D76: 50 | E76: mg | F76: 325 | G76: =BANDAS!$E$44*$D76 | H76: =BANDAS!$F$44*$D76 | I76: =ROUND(AVERAGE(G76,H76)/1,0)*1 | J76: =IF($D76=0,"",I76/$D76) | K76: =IF(F76="","",IF(F76<G76,"POR DEBAJO",IF(F76>H76,"POR ENCIMA","EN MERCADO"))) | L76: V
A77: FITNESS | B77: RT | C77: Retatrutide | D77: 60 | E77: mg | F77: 390 | G77: =BANDAS!$E$44*$D77 | H77: =BANDAS!$F$44*$D77 | I77: =ROUND(AVERAGE(G77,H77)/1,0)*1 | J77: =IF($D77=0,"",I77/$D77) | K77: =IF(F77="","",IF(F77<G77,"POR DEBAJO",IF(F77>H77,"POR ENCIMA","EN MERCADO"))) | L77: V
A78: FITNESS | B78: 2S | C78: SS-31 | D78: 10 | E78: mg | F78: 40 | G78: =BANDAS!$E$45*$D78 | H78: =BANDAS!$F$45*$D78 | I78: =ROUND(AVERAGE(G78,H78)/1,0)*1 | J78: =IF($D78=0,"",I78/$D78) | K78: =IF(F78="","",IF(F78<G78,"POR DEBAJO",IF(F78>H78,"POR ENCIMA","EN MERCADO"))) | L78: D
A79: FITNESS | B79: 2S | C79: SS-31 | D79: 50 | E79: mg | F79: 210 | G79: =BANDAS!$E$45*$D79 | H79: =BANDAS!$F$45*$D79 | I79: =ROUND(AVERAGE(G79,H79)/1,0)*1 | J79: =IF($D79=0,"",I79/$D79) | K79: =IF(F79="","",IF(F79<G79,"POR DEBAJO",IF(F79>H79,"POR ENCIMA","EN MERCADO"))) | L79: D
A80: FITNESS | B80: SM | C80: Semaglutide | D80: 5 | E80: mg | F80: 20 | G80: =BANDAS!$E$46*$D80 | H80: =BANDAS!$F$46*$D80 | I80: =ROUND(AVERAGE(G80,H80)/1,0)*1 | J80: =IF($D80=0,"",I80/$D80) | K80: =IF(F80="","",IF(F80<G80,"POR DEBAJO",IF(F80>H80,"POR ENCIMA","EN MERCADO"))) | L80: V
A81: FITNESS | B81: SM | C81: Semaglutide | D81: 10 | E81: mg | F81: 40 | G81: =BANDAS!$E$46*$D81 | H81: =BANDAS!$F$46*$D81 | I81: =ROUND(AVERAGE(G81,H81)/1,0)*1 | J81: =IF($D81=0,"",I81/$D81) | K81: =IF(F81="","",IF(F81<G81,"POR DEBAJO",IF(F81>H81,"POR ENCIMA","EN MERCADO"))) | L81: V
A82: FITNESS | B82: SM | C82: Semaglutide | D82: 15 | E82: mg | F82: 60 | G82: =BANDAS!$E$46*$D82 | H82: =BANDAS!$F$46*$D82 | I82: =ROUND(AVERAGE(G82,H82)/1,0)*1 | J82: =IF($D82=0,"",I82/$D82) | K82: =IF(F82="","",IF(F82<G82,"POR DEBAJO",IF(F82>H82,"POR ENCIMA","EN MERCADO"))) | L82: V
A83: FITNESS | B83: SM | C83: Semaglutide | D83: 20 | E83: mg | F83: 80 | G83: =BANDAS!$E$46*$D83 | H83: =BANDAS!$F$46*$D83 | I83: =ROUND(AVERAGE(G83,H83)/1,0)*1 | J83: =IF($D83=0,"",I83/$D83) | K83: =IF(F83="","",IF(F83<G83,"POR DEBAJO",IF(F83>H83,"POR ENCIMA","EN MERCADO"))) | L83: V
A84: FITNESS | B84: SM | C84: Semaglutide | D84: 30 | E84: mg | F84: 115 | G84: =BANDAS!$E$46*$D84 | H84: =BANDAS!$F$46*$D84 | I84: =ROUND(AVERAGE(G84,H84)/1,0)*1 | J84: =IF($D84=0,"",I84/$D84) | K84: =IF(F84="","",IF(F84<G84,"POR DEBAJO",IF(F84>H84,"POR ENCIMA","EN MERCADO"))) | L84: V
A85: FITNESS | B85: SMO | C85: Sermorelin | D85: 5 | E85: mg | F85: 30 | G85: =BANDAS!$E$47*$D85 | H85: =BANDAS!$F$47*$D85 | I85: =ROUND(AVERAGE(G85,H85)/1,0)*1 | J85: =IF($D85=0,"",I85/$D85) | K85: =IF(F85="","",IF(F85<G85,"POR DEBAJO",IF(F85>H85,"POR ENCIMA","EN MERCADO"))) | L85: D
A86: FITNESS | B86: SMO | C86: Sermorelin | D86: 10 | E86: mg | F86: 55 | G86: =BANDAS!$E$47*$D86 | H86: =BANDAS!$F$47*$D86 | I86: =ROUND(AVERAGE(G86,H86)/1,0)*1 | J86: =IF($D86=0,"",I86/$D86) | K86: =IF(F86="","",IF(F86<G86,"POR DEBAJO",IF(F86>H86,"POR ENCIMA","EN MERCADO"))) | L86: D
A87: FITNESS | B87: TB | C87: TB-500 | D87: 5 | E87: mg | F87: 22 | G87: =BANDAS!$E$48*$D87 | H87: =BANDAS!$F$48*$D87 | I87: =ROUND(AVERAGE(G87,H87)/1,0)*1 | J87: =IF($D87=0,"",I87/$D87) | K87: =IF(F87="","",IF(F87<G87,"POR DEBAJO",IF(F87>H87,"POR ENCIMA","EN MERCADO"))) | L87: V
A88: FITNESS | B88: TB | C88: TB-500 | D88: 10 | E88: mg | F88: 35 | G88: =BANDAS!$E$48*$D88 | H88: =BANDAS!$F$48*$D88 | I88: =ROUND(AVERAGE(G88,H88)/1,0)*1 | J88: =IF($D88=0,"",I88/$D88) | K88: =IF(F88="","",IF(F88<G88,"POR DEBAJO",IF(F88>H88,"POR ENCIMA","EN MERCADO"))) | L88: V
A89: FITNESS | B89: TSM | C89: Tesamorelin | D89: 5 | E89: mg | F89: 25 | G89: =BANDAS!$E$49*$D89 | H89: =BANDAS!$F$49*$D89 | I89: =ROUND(AVERAGE(G89,H89)/1,0)*1 | J89: =IF($D89=0,"",I89/$D89) | K89: =IF(F89="","",IF(F89<G89,"POR DEBAJO",IF(F89>H89,"POR ENCIMA","EN MERCADO"))) | L89: D
A90: FITNESS | B90: TSM | C90: Tesamorelin | D90: 10 | E90: mg | F90: 50 | G90: =BANDAS!$E$49*$D90 | H90: =BANDAS!$F$49*$D90 | I90: =ROUND(AVERAGE(G90,H90)/1,0)*1 | J90: =IF($D90=0,"",I90/$D90) | K90: =IF(F90="","",IF(F90<G90,"POR DEBAJO",IF(F90>H90,"POR ENCIMA","EN MERCADO"))) | L90: D
A91: FITNESS | B91: TSM | C91: Tesamorelin | D91: 20 | E91: mg | F91: 100 | G91: =BANDAS!$E$49*$D91 | H91: =BANDAS!$F$49*$D91 | I91: =ROUND(AVERAGE(G91,H91)/1,0)*1 | J91: =IF($D91=0,"",I91/$D91) | K91: =IF(F91="","",IF(F91<G91,"POR DEBAJO",IF(F91>H91,"POR ENCIMA","EN MERCADO"))) | L91: D
A92: FITNESS | B92: TR | C92: Tirzepatide | D92: 5 | E92: mg | F92: 20 | G92: =BANDAS!$E$50*$D92 | H92: =BANDAS!$F$50*$D92 | I92: =ROUND(AVERAGE(G92,H92)/1,0)*1 | J92: =IF($D92=0,"",I92/$D92) | K92: =IF(F92="","",IF(F92<G92,"POR DEBAJO",IF(F92>H92,"POR ENCIMA","EN MERCADO"))) | L92: V
A93: FITNESS | B93: TR | C93: Tirzepatide | D93: 10 | E93: mg | F93: 40 | G93: =BANDAS!$E$50*$D93 | H93: =BANDAS!$F$50*$D93 | I93: =ROUND(AVERAGE(G93,H93)/1,0)*1 | J93: =IF($D93=0,"",I93/$D93) | K93: =IF(F93="","",IF(F93<G93,"POR DEBAJO",IF(F93>H93,"POR ENCIMA","EN MERCADO"))) | L93: V
A94: FITNESS | B94: TR | C94: Tirzepatide | D94: 15 | E94: mg | F94: 60 | G94: =BANDAS!$E$50*$D94 | H94: =BANDAS!$F$50*$D94 | I94: =ROUND(AVERAGE(G94,H94)/1,0)*1 | J94: =IF($D94=0,"",I94/$D94) | K94: =IF(F94="","",IF(F94<G94,"POR DEBAJO",IF(F94>H94,"POR ENCIMA","EN MERCADO"))) | L94: V
A95: FITNESS | B95: TR | C95: Tirzepatide | D95: 20 | E95: mg | F95: 80 | G95: =BANDAS!$E$50*$D95 | H95: =BANDAS!$F$50*$D95 | I95: =ROUND(AVERAGE(G95,H95)/1,0)*1 | J95: =IF($D95=0,"",I95/$D95) | K95: =IF(F95="","",IF(F95<G95,"POR DEBAJO",IF(F95>H95,"POR ENCIMA","EN MERCADO"))) | L95: V
A96: FITNESS | B96: TR | C96: Tirzepatide | D96: 30 | E96: mg | F96: 125 | G96: =BANDAS!$E$50*$D96 | H96: =BANDAS!$F$50*$D96 | I96: =ROUND(AVERAGE(G96,H96)/1,0)*1 | J96: =IF($D96=0,"",I96/$D96) | K96: =IF(F96="","",IF(F96<G96,"POR DEBAJO",IF(F96>H96,"POR ENCIMA","EN MERCADO"))) | L96: V
A97: FITNESS | B97: TR | C97: Tirzepatide | D97: 40 | E97: mg | F97: 165 | G97: =BANDAS!$E$50*$D97 | H97: =BANDAS!$F$50*$D97 | I97: =ROUND(AVERAGE(G97,H97)/1,0)*1 | J97: =IF($D97=0,"",I97/$D97) | K97: =IF(F97="","",IF(F97<G97,"POR DEBAJO",IF(F97>H97,"POR ENCIMA","EN MERCADO"))) | L97: V
A98: FITNESS | B98: TR | C98: Tirzepatide | D98: 50 | E98: mg | F98: 205 | G98: =BANDAS!$E$50*$D98 | H98: =BANDAS!$F$50*$D98 | I98: =ROUND(AVERAGE(G98,H98)/1,0)*1 | J98: =IF($D98=0,"",I98/$D98) | K98: =IF(F98="","",IF(F98<G98,"POR DEBAJO",IF(F98>H98,"POR ENCIMA","EN MERCADO"))) | L98: V
A99: FITNESS | B99: TR | C99: Tirzepatide | D99: 60 | E99: mg | F99: 245 | G99: =BANDAS!$E$50*$D99 | H99: =BANDAS!$F$50*$D99 | I99: =ROUND(AVERAGE(G99,H99)/1,0)*1 | J99: =IF($D99=0,"",I99/$D99) | K99: =IF(F99="","",IF(F99<G99,"POR DEBAJO",IF(F99>H99,"POR ENCIMA","EN MERCADO"))) | L99: V
A100: LONGEVITY | B100: CTL | C100: Cartalax | D100: 20 | E100: mg | F100: 110 | G100: =BANDAS!$E$51*$D100 | H100: =BANDAS!$F$51*$D100 | I100: =ROUND(AVERAGE(G100,H100)/1,0)*1 | J100: =IF($D100=0,"",I100/$D100) | K100: =IF(F100="","",IF(F100<G100,"POR DEBAJO",IF(F100>H100,"POR ENCIMA","EN MERCADO"))) | L100: D
A101: LONGEVITY | B101: DS | C101: DSIP | D101: 5 | E101: mg | F101: 15 | G101: =BANDAS!$E$52*$D101 | H101: =BANDAS!$F$52*$D101 | I101: =ROUND(AVERAGE(G101,H101)/1,0)*1 | J101: =IF($D101=0,"",I101/$D101) | K101: =IF(F101="","",IF(F101<G101,"POR DEBAJO",IF(F101>H101,"POR ENCIMA","EN MERCADO"))) | L101: D
A102: LONGEVITY | B102: DS | C102: DSIP | D102: 10 | E102: mg | F102: 35 | G102: =BANDAS!$E$52*$D102 | H102: =BANDAS!$F$52*$D102 | I102: =ROUND(AVERAGE(G102,H102)/1,0)*1 | J102: =IF($D102=0,"",I102/$D102) | K102: =IF(F102="","",IF(F102<G102,"POR DEBAJO",IF(F102>H102,"POR ENCIMA","EN MERCADO"))) | L102: D
...

Sheet BANDAS
B2: BANDAS DE MERCADO
B3: Precio de mercado por unidad, en dólares. Es el único sitio donde hay números escritos a mano: todo lo demás del libro sale de aquí por fórmula.
B5: Tipo de cambio USD → MXN | E5: 17.5 | F5: Fuente: Investing.com · media 2026 ≈ 17.47
B6: Prima del retail mexicano sobre el estadounidense | E6: 1.35 | F6: Mediana observada comparando ocho pares MX/USA reales (ver FUENTES)
A8: CÓDIGO | B8: COMPUESTO | C8: LÍNEA | D8: UNIDAD | E8: USD/UNIDAD BAJO | F8: USD/UNIDAD ALTO | G8: CONF. | H8: DE DÓNDE SALE
A9: AC | B9: AHK-Cu | C9: BEAUTY | D9: mg | E9: 0.7 | F9: 1.3 | G9: D | H9: AHK-Cu: 50 mg $35–65, sigue a GHK-Cu con prima
A10: CU | B10: GHK-Cu | C10: BEAUTY | D10: mg | E10: 0.5 | F10: 0.8 | G10: V | H10: peptide.promo · GHK-Cu desde $0.50/mg; 50 mg $20–40
A11: GL | B11: GLOW Blend | C11: BEAUTY | D11: mg | E11: 1.7 | F11: 3.1 | G11: D | H11: Mezcla GLOW 70 mg: $120–220 el vial
A12: GT | B12: Glutathione | C12: BEAUTY | D12: mg | E12: 0.05 | F12: 0.1 | G12: D | H12: Glutatión: 600 mg $30–60, es materia prima
A13: KL | B13: KLOW Blend | C13: BEAUTY | D13: mg | E13: 1.9 | F13: 3.25 | G13: D | H13: Mezcla KLOW 80 mg: $150–260 el vial
A14: KP | B14: KPV | C14: BEAUTY | D14: mg | E14: 3 | F14: 5.5 | G14: D | H14: KPV: 10 mg $30–55
A15: MX | B15: Matrixyl | C15: BEAUTY | D15: mg | E15: 5 | F15: 9 | G15: D | H15: Matrixyl: 10 mg $50–90
A16: MT1 | B16: Melanotan I | C16: BEAUTY | D16: mg | E16: 3 | F16: 5.5 | G16: D | H16: Melanotán 1: sigue a melanotán 2 con menos demanda
A17: MT2 | B17: Melanotan II | C17: BEAUTY | D17: mg | E17: 2.2 | F17: 6.4 | G17: V | H17: nationwidepeptides · melanotán 2 $22–30 y $47–64 según presentación
A18: OT | B18: Oxytocin | C18: BEAUTY | D18: mg | E18: 5 | F18: 9 | G18: D | H18: Oxitocina: 5 mg $25–45
A19: PT | B19: PT-141 | C19: BEAUTY | D19: mg | E19: 4 | F19: 8 | G19: V | H19: biotechpeptides / nexaph · PT-141 10 mg; nexaph $160 es el techo del mercado
A20: NP8 | B20: Snap-8 | C20: BEAUTY | D20: mg | E20: 3 | F20: 5.5 | G20: D | H20: Snap-8: 10 mg $30–55
... A64: B12 | B64: Vitamin B12 | C64: LONGEVITY | D64: mg | E64: 15 | F64: 30 | G64: D | H64: Vitamina B12 por vial de 1 mg/ml: $15–30

Sheet FUENTES
B2: FUENTES
B3: Cada enlace consultado y qué dato salió de él. Consultado el 02.08.2026. Los precios de este mercado se mueven semana a semana: conviene volver cada trimestre.
A5: MERCADO | B5: FUENTE | C5: QUÉ DATO DIO | D5: ENLACE
A6: USA | B6: peptide.promo | C6: Comparador $/mg. Semaglutida $2.75/mg · tirzepatida $3.09/mg · BPC-157 $2.46/mg · GHK-Cu $0.50/mg · NAD+ $0.14/mg | D6: https://peptide.promo/
A7: USA | B7: PeptidesExplorer | C7: Rangos por vial: semaglutida 5 mg $20–40 · tirzepatida 5 mg $20–45 · retatrutida 5 mg $24–50 · BPC-157 5 mg $20–35 · GHK-Cu 50 mg $20–40 | D7: https://peptidesexplorer.com/blog/how-much-do-peptides-cost
A8: USA | B8: PeptiLab Research | C8: BPC-157 10 mg $22.79 · TB-500 10 mg $29.99 · epitalón 10 mg $13.79 · retatrutida 10 mg $56.40 (con descuento) | D8: https://peptilabresearch.com/shop/
A9: USA | B9: peptideprices.net | C9: Comparador $/10 mg sobre 51 vendedores, con COA y fecha de comprobación por listado | D9: https://peptideprices.net/
A10: USA | B10: PepsTracker | C10: Comparador sobre 24 vendedores; volatilidad semanal de tirzepatida y retatrutida | D10: https://pepstracker.com/
A11: USA | B11: The Peptide Catalog | C11: Índice de precios trimestral, tendencia a 90 días | D11: https://thepeptidecatalog.com/articles/peptide-pricing-report-q1-2026
A12: USA | B12: PeptideDeck | C12: BPC-157 $49–100 por vial en 2026; $5–8/mg de vendedor legítimo; por debajo de $3/mg es señal de alarma | D12: https://www.peptidedeck.com/blog/bpc-157-for-sale
A13: USA | B13: Biotech Peptides | C13: Precio de lista de BPC-157 5 mg y mezcla CJC-1295 + Ipamorelina 10 mg | D13: https://biotechpeptides.com/product/bpc-157/
A14: USA | B14: Nationwide Peptides | C14: Melanotán 2: $22–30 y $47–64 según presentación | D14: https://www.nationwidepeptides.com/products/melanotan-2/
A15: USA | B15: NEXAPH | C15: PT-141 $160 — techo del mercado, útil como referencia superior | D15: https://nexaph.com/
A16: USA | B16: Peptide Pros | C16: Catálogo de secretagogos GH: GHRP-2 5 mg, GHRP-6 5 mg, hexarelina 2 mg, ipamorelina 2 mg, sermorelina 2 mg, tesamorelina 5 mg | D16: https://www.peptidepros.net/
... A26: Tipo de cambio | B26: Investing.com | C26: USD/MXN 17.35 al cierre consultado; media 2026 ≈ 17.47. En el libro se usa 17.50 | D26: https://es.investing.com/currencies/usd-mxn-historical-data
B28: NOTA SOBRE EL MÉTODO
B29: · El acceso directo a las tiendas está bloqueado desde este entorno, así que los precios se han triangulado con buscador sobre varios comparadores y fichas de producto en lugar de leerse de la tienda una por una.
B30: · Por eso el libro separa V de D en vez de dar todo por igual: donde hay una cifra publicada para ese compuesto se marca V; donde no la hay, se usa la banda de su clase y se marca D.
B31: · Antes de fijar precio en los diez compuestos que más vendas, conviene abrir esos enlaces y confirmar el número del día. Son diez comprobaciones, no ciento dieciocho.
